Workbook

Sheet Balance Sheet 
B2: Particulars | C2: Notes | E2: FY21 | F2: FY22 | G2: FY23 | H2: FY24 | I2: FY25 | J2: FY26E | K2: FY27E | L2: FY28E | M2: FY29E | N2: FY30E
B4: Non-Current Assets
A5: Capex Schedule | B5: Property, Plant and Equipment | E5: 5550.67 | F5: 5354.34 | G5: 5159.42 | H5: 5212.58 | I5: 5219.13 | J5: ='Schedule Populated '!J4 -> 5622.7723 | K5: ='Schedule Populated '!K4 -> 6126.482 | L5: ='Schedule Populated '!L4 -> 6664.6926 | M5: ='Schedule Populated '!M4 -> 7242.9201 | N5: ='Schedule Populated '!N4 -> 7868.2906
A6: Assumptions | B6: Capital work-in-progress | E6: 236.4 | F6: 149.13 | G6: 122.09 | H6: 127.16 | I6: 105.37 | J6: =Assumptions!J27 -> 131.058 | K6: =Assumptions!K27 -> 123.8722 | L6: =Assumptions!L27 -> 124.32828 | M6: =Assumptions!M27 -> 123.25177 | N6: =Assumptions!N27 -> 122.62921
A7: Capex Schedule | B7: Right-of-use Assets | E7: 511.24 | F7: 517.9 | G7: 481.28 | H7: 475.97 | I7: 483.39 | J7: ='Schedule Populated '!J5 -> 519.4885 | K7: ='Schedule Populated '!K5 -> 555.6034 | L7: ='Schedule Populated '!L5 -> 583.34714 | M7: ='Schedule Populated '!M5 -> 616.0817 | N7: ='Schedule Populated '!N5 -> 651.33107
A8: Capex Schedule | B8: Other Intangible assets | E8: 318.48 | F8: 321.3 | G8: 518.5 | H8: 543.65 | I8: 580.46 | J8: ='Schedule Populated '!J6 -> 779.2849 | K8: ='Schedule Populated '!K6 -> 848.41352 | L8: ='Schedule Populated '!L6 -> 927.63771 | M8: ='Schedule Populated '!M6 -> 1019.7033 | N8: ='Schedule Populated '!N6 -> 1135.9969
A9: Assumptions | B9: Intangible assets under development | E9: 258.73 | F9: 368.09 | G9: 331.62 | H9: 356.9 | I9: 381.81 | J9: =Assumptions!J28 -> 355.638 | K9: =Assumptions!K28 -> 362.4592 | L9: =Assumptions!L28 -> 358.70808 | M9: =Assumptions!M28 -> 361.65579 | N9: =Assumptions!N28 -> 362.26546
A10: Assumptions | B10: Equity accounted investments in associates | E10: 2407.69 | F10: 2202.51 | G10: 2618.7 | H10: 3083.59 | I10: 2980.94 | J10: =Assumptions!J29 -> 2840.343 | K10: =Assumptions!K29 -> 2820.8992 | L10: =Assumptions!L29 -> 2848.7856 | M10: =Assumptions!M29 -> 2876.2713 | N10: =Assumptions!N29 -> 2869.3624
B11: Financial Assets
A12: Assumptions | B12: i) Investments | E12: 1948.59 | F12: 2455.05 | G12: 4600.38 | H12: 5362.57 | I12: 4767.33 | J12: =Assumptions!J31 -> 4416.105 | K12: =Assumptions!K31 -> 4438.441 | L12: =Assumptions!L31 -> 4573.2359 | M12: =Assumptions!M31 -> 4615.4272 | N12: =Assumptions!N31 -> 4580.3292
A13: Assumptions | B13: ii) Loans | E13: 16.73 | F13: 17.43 | G13: 19.87 | H13: 21.15 | I13: 24.87 | J13: =Assumptions!J32 -> 21.696 | K13: =Assumptions!K32 -> 21.9844 | L13: =Assumptions!L32 -> 21.89156 | M13: =Assumptions!M32 -> 22.123544 | N13: =Assumptions!N32 -> 22.271926
A14: Assumptions | B14: iii) Others | E14: 35.91 | F14: 42.01 | G14: 206.09 | H14: 189.44 | I14: 47.09 | J14: =Assumptions!J33 -> 104.069 | K14: =Assumptions!K33 -> 99.5086 | L14: =Assumptions!L33 -> 115.28614 | M14: =Assumptions!M33 -> 110.02694 | N14: =Assumptions!N33 -> 103.66338
A15: Assumptions | B15: Income Tax Assets (Net) | E15: 378.49 | F15: 358.07 | G15: 270.69 | H15: 335.68 | I15: 254.49 | J15: =Assumptions!J34 -> 303.225 | K15: =Assumptions!K34 -> 294.081 | L15: =Assumptions!L34 -> 294.6859 | M15: =Assumptions!M34 -> 295.43816 | N15: =Assumptions!N34 -> 291.76063
A16: Assumptions | B16: Other Non-current Assets | E16: 62.68 | F16: 120.34 | G16: 153.06 | H16: 128.65 | I16: 111.55 | J16: =Assumptions!J35 -> 116.823 | K16: =Assumptions!K35 -> 120.3992 | L16: =Assumptions!L35 -> 122.53258 | M16: =Assumptions!M35 -> 120.83509 | N16: =Assumptions!N35 -> 119.97103
B17: Total Non-current Assets | E17: =SUM(E4:E16) -> 11725.61 | F17: =SUM(F4:F16) -> 11906.17 | G17: =SUM(G4:G16) -> 14481.7 | H17: =SUM(H4:H16) -> 15837.34 | I17: =SUM(I4:I16) -> 14956.43 | J17: =SUM(J4:J16) -> 15210.503 | K17: =SUM(K4:K16) -> 15812.144 | L17: =SUM(L4:L16) -> 16635.131 | ... N17: =SUM(N4:N16) -> 18127.872
B19: Current Assets
A20: WC Schedule | B20: Inventories | E20: 1789.27 | F20: 1472.41 | G20: 1756.39 | H20: 1755.9 | I20: 2013.34 | J20: ='Schedule Populated '!J82 -> 2334.6416 | K20: ='Schedule Populated '!K82 -> 2584.2506 | L20: ='Schedule Populated '!L82 -> 2856.664 | M20: ='Schedule Populated '!M82 -> 3140.9796 | N20: ='Schedule Populated '!N82 -> 3468.6563
B21: Financial Assets
A22: WC Schedule | B22: i) Investments | E22: 6225.34 | F22: 5870.31 | G22: 3671.85 | H22: 4305.08 | I22: 6635.99 | J22: ='Schedule Populated '!J84 -> 7062.4459 | K22: ='Schedule Populated '!K84 -> 7889.1709 | L22: ='Schedule Populated '!L84 -> 8318.0845 | M22: ='Schedule Populated '!M84 -> 9299.7638 | N22: ='Schedule Populated '!N84 -> 10389.496
A23: WC Schedule | B23: ii) Trade Receivables | E23: 2274.68 | F23: 2158.49 | G23: 2719.47 | H23: 2630.22 | I23: 3381.29 | J23: ='Schedule Populated '!J85 -> 3608.2971 | K23: ='Schedule Populated '!K85 -> 4065.6725 | L23: ='Schedule Populated '!L85 -> 4472.9614 | M23: ='Schedule Populated '!M85 -> 4934.3841 | N23: ='Schedule Populated '!N85 -> 5473.2641
B24: iii) Cash and Cash Equivalents | E24: =274.62+121.62 -> 396.24 | F24: =181.02+118.72 -> 299.74 | G24: =226.3+196.5 -> 422.8 | H24: =604.91+91.56 -> 696.47 | I24: =383.55+190.53 -> 574.08 | J24: =CFS!E22 -> 9521.4997 | K24: =CFS!F22 -> 14091.617 | L24: =CFS!G22 -> 20480.93 | M24: =CFS!H22 -> 26586.193 | N24: =CFS!I22 -> 32895.555
A26: WC Schedule | B26: v) Loans | E26: 22.95 | F26: 22.81 | G26: 23.71 | H26: 24.56 | I26: 27.07 | J26: ='Schedule Populated '!J86 -> 32.075261 | K26: ='Schedule Populated '!K86 -> 35.735237 | L26: ='Schedule Populated '!L86 -> 39.261237 | M26: ='Schedule Populated '!M86 -> 43.225673 | N26: ='Schedule Populated '!N86 -> 47.621582
A27: WC Schedule | B27: vi) Others | E27: 382.55 | F27: 475 | G27: 571.65 | H27: 423.53 | I27: 141.59 | J27: ='Schedule Populated '!J87 -> 436.99162 | K27: ='Schedule Populated '!K87 -> 479.47183 | L27: ='Schedule Populated '!L87 -> 555.24343 | M27: ='Schedule Populated '!M87 -> 574.7219 | N27: ='Schedule Populated '!N87 -> 609.8836
A28: WC Schedule | B28: Income tax assets (net) | E28: 0 | F28: 0 | G28: 0 | H28: 0 | I28: 198.12 | J28: ='Schedule Populated '!J88 -> 91.200606 | K28: ='Schedule Populated '!K88 -> 116.47842 | L28: ='Schedule Populated '!L88 -> 113.23148 | M28: ='Schedule Populated '!M88 -> 136.18913 | N28: ='Schedule Populated '!N88 -> 164.68574
A29: WC Schedule | B29: Other current assets | E29: 279.45 | F29: 273.46 | G29: 269.46 | H29: 479.69 | I29: 462.41 | J29: ='Schedule Populated '!J89 -> 515.88668 | K29: ='Schedule Populated '!K89 -> 563.00712 | L29: ='Schedule Populated '!L89 -> 624.09651 | M29: ='Schedule Populated '!M89 -> 706.22302 | N29: ='Schedule Populated '!N89 -> 771.14997
B30: Total Current Assets | E30: =SUM(E20:E29) -> 11370.48 | F30: =SUM(F20:F29) -> 10572.22 | G30: =SUM(G20:G29) -> 9435.33 | H30: =SUM(H20:H29) -> 10315.45 | I30: =SUM(I20:I29) -> 13433.89 | J30: =SUM(J20:J29) -> 23603.039 | K30: =SUM(K20:K29) -> 29825.403 | L30: =SUM(L20:L29) -> 37460.472 | ... N30: =SUM(N20:N29) -> 53820.312
B31: Total Assets | E31: =E17+E30 -> 23096.09 | F31: =F17+F30 -> 22478.39 | G31: =G17+G30 -> 23917.03 | H31: =H17+H30 -> 26152.79 | I31: =I17+I30 -> 28390.32 | J31: =J17+J30 -> 38813.541 | K31: =K17+K30 -> 45637.547 | L31: =L17+L30 -> 54095.604 | ... N31: =N17+N30 -> 71948.184
B32: Equities and Liabilities
B33: Equity
A34: Assumptions | B34: i) Equity Share Capital | E34: 39.96 | F34: 39.96 | G34: 39.97 | H34: 39.98 | I34: 40 | J34: =Assumptions!J37 -> 40 | K34: =Assumptions!K37 -> 40 | L34: =Assumptions!L37 -> 40 | M34: =Assumptions!M37 -> 40 | N34: =Assumptions!N37 -> 40
A35: Assumptions | B35: iii) Other Equity | E35: 15376.46 | F35: 15806.69 | G35: 16615.6 | H35: 17658.94 | I35: 19232.04 | J35: =Assumptions!J38 -> 24461.429 | K35: =Assumptions!K38 -> 30485.429 | L35: =Assumptions!L38 -> 37037.013 | M35: =Assumptions!M38 -> 44366.378 | N35: =Assumptions!N38 -> 52213.487
A36: Assumptions | B36: Non - Controlling Interests | E36: 143.19 | F36: 148.05 | G36: 125.06 | H36: 135.65 | I36: 132.05 | J36: =Assumptions!J39 -> 135.145 | K36: =Assumptions!K39 -> 134.549 | L36: =Assumptions!L39 -> 133.6391 | M36: =Assumptions!M39 -> 134.10484 | N36: =Assumptions!N39 -> 133.90807
B37: Total Equity | E37: =SUM(E34:E36) -> 15559.61 | F37: =SUM(F34:F36) -> 15994.7 | G37: =SUM(G34:G36) -> 16780.63 | H37: =SUM(H34:H36) -> 17834.57 | I37: =SUM(I34:I36) -> 19404.09 | J37: =SUM(J34:J36) -> 24636.574 | K37: =SUM(K34:K36) -> 30659.978 | L37: =SUM(L34:L36) -> 37210.652 | ... N37: =SUM(N34:N36) -> 52387.395
B38: Liabilities
B39: Non-current Liabilities
B40: Financial Liabilities
A41: WC Schedule | B41: i) Borrowings | E41: 45.18 | F41: 36.17 | G41: 20.09 | H41: - | I41: - | J41: ='Schedule Populated '!J51 -> 1.0045 | K41: ='Schedule Populated '!K51 -> 1.0045 | L41: ='Schedule Populated '!L51 -> 1.0045 | M41: ='Schedule Populated '!M51 -> 1.054725 | N41: ='Schedule Populated '!N51 -> 1.10495
A42: WC Schedule | B42: ii) Lease Liabilities | E42: 212.42 | F42: 215.51 | G42: 219.67 | H42: 199.13 | I42: 196.21 | J42: ='Schedule Populated '!J55 -> 206.0205 | K42: ='Schedule Populated '!K55 -> 216.32153 | L42: ='Schedule Populated '!L55 -> 227.1376 | M42: ='Schedule Populated '!M55 -> 238.49448 | N42: ='Schedule Populated '!N55 -> 250.41921
A43: Assumptions | B43: iii) Other Financial Liabilities | E43: 146.04 | F43: 155.04 | G43: 196.29 | H43: 178.13 | I43: 143.83 | J43: =Assumptions!J41 -> 160.708 | K43: =Assumptions!K41 -> 160.3782 | L43: =Assumptions!L41 -> 164.18868 | M43: =Assumptions!M41 -> 162.05573 | N43: =Assumptions!N41 -> 160.57052
A44: Assumptions | B44: Provisions | E44: 175.57 | F44: 181.13 | G44: 201.94 | H44: 322.46 | I44: 495.29 | J44: =Assumptions!J42 -> 350.718 | K44: =Assumptions!K42 -> 359.4272 | L44: =Assumptions!L42 -> 350.95528 | M44: =Assumptions!M42 -> 365.05707 | N44: =Assumptions!N42 -> 371.85293
A45: Assumptions | B45: Deferred Tax Liabilities (Net) | E45: 452.74 | F45: 378.21 | G45: 485.79 | H45: 570.13 | I45: 674.92 | J45: =Assumptions!J43 -> 572.681 | K45: =Assumptions!K43 -> 574.9614 | L45: =Assumptions!L43 -> 574.87286 | M45: =Assumptions!M43 -> 584.21066 | N45: =Assumptions!N43 -> 588.40236
B46: Total Non-current Liabilities | E46: =SUM(E41:E45) -> 1031.95 | F46: =SUM(F41:F45) -> 966.06 | G46: =SUM(G41:G45) -> 1123.78 | H46: =SUM(H41:H45) -> 1269.85 | I46: =SUM(I41:I45) -> 1510.25 | J46: =SUM(J41:J45) -> 1291.132 | K46: =SUM(K41:K45) -> 1312.0928 | L46: =SUM(L41:L45) -> 1318.1589 | ... N46: =SUM(N41:N45) -> 1372.35
B47: Current Liabilities
B48: Financial Liabilities
A49: WC Schedule | B49: i) Borrowings | E49: 296.85 | F49: 317.31 | G49: 293.15 | H49: 363.43 | I49: 456.76 | J49: ='Schedule Populated '!J93 -> 482.78834 | K49: ='Schedule Populated '!K93 -> 541.51122 | L49: ='Schedule Populated '!L93 -> 587.77754 | M49: ='Schedule Populated '!M93 -> 657.2064 | N49: ='Schedule Populated '!N93 -> 727.50327
A50: WC Schedule | B50: ii) Lease Liabilities | E50: 29.57 | F50: 36.18 | G50: 34.63 | H50: 43.85 | I50: 46.96 | J50: ='Schedule Populated '!J94 -> 53.108044 | K50: ='Schedule Populated '!K94 -> 59.436858 | L50: ='Schedule Populated '!L94 -> 65.131493 | M50: ='Schedule Populated '!M94 -> 72.598194 | N50: ='Schedule Populated '!N94 -> 79.751247
A51: WC Schedule | B51: iii) Trade Payables – MSME | E51: 16.68 | F51: 26.19 | G51: 2.44 | H51: 18.74 | I51: 21.5 | J51: ='Schedule Populated '!J95 -> 23.992804 | K51: ='Schedule Populated '!K95 -> 26.550806 | L51: ='Schedule Populated '!L95 -> 26.929599 | M51: ='Schedule Populated '!M95 -> 31.447494 | N51: ='Schedule Populated '!N95 -> 34.532949
A52: WC Schedule | B52: iv) Trade Payables – Others | E52: 5247.5 | F52: 4316.9 | G52: 4757.7 | H52: 5604.16 | I52: 5678.16 | J52: ='Schedule Populated '!J96 -> 6858.1797 | K52: ='Schedule Populated '!K96 -> 7499.5803 | L52: ='Schedule Populated '!L96 -> 8317.8208 | M52: ='Schedule Populated '!M96 -> 9199.1083 | N52: ='Schedule Populated '!N96 -> 10097.262
A53: WC Schedule | B53: v) Other Financial Liabilities | E53: 167.52 | F53: 145.58 | G53: 169.93 | H53: 254.9 | I53: 282.94 | J53: ='Schedule Populated '!J97 -> 4374.5974 | K53: ='Schedule Populated '!K97 -> 4327.6306 | L53: ='Schedule Populated '!L97 -> 5234.2919 | M53: ='Schedule Populated '!M97 -> 5490.3948 | N53: ='Schedule Populated '!N97 -> 5612.5266
A54: WC Schedule | B54: Other Current Liabilities | E54: 570.59 | F54: 496.32 | G54: 562.09 | H54: 603.85 | I54: 768.17 | J54: ='Schedule Populated '!J98 -> 521.2592 | K54: ='Schedule Populated '!K98 -> 613.4183 | L54: ='Schedule Populated '!L98 -> 640.34505 | M54: ='Schedule Populated '!M98 -> 742.38567 | N54: ='Schedule Populated '!N98 -> 853.20606
A55: WC Schedule | B55: Provisions | E55: 175.82 | F55: 179.15 | G55: 192.68 | H55: 159.44 | I55: 221.49 | J55: ='Schedule Populated '!J99 -> 571.90982 | K55: ='Schedule Populated '!K99 -> 597.34777 | L55: ='Schedule Populated '!L99 -> 694.49695 | M55: ='Schedule Populated '!M99 -> 740.91933 | N55: ='Schedule Populated '!N99 -> 783.65653
B56: Total Current Liabilities | E56: =SUM(E49:E55) -> 6504.53 | F56: =SUM(F49:F55) -> 5517.63 | G56: =SUM(G49:G55) -> 6012.62 | H56: =SUM(H49:H55) -> 7048.37 | I56: =SUM(I49:I55) -> 7475.98 | J56: =SUM(J49:J55) -> 12885.835 | K56: =SUM(K49:K55) -> 13665.476 | L56: =SUM(L49:L55) -> 15566.793 | ... N56: =SUM(N49:N55) -> 18188.439
B57: Total Liabilities | E57: =E46+E56 -> 7536.48 | F57: =F46+F56 -> 6483.69 | G57: =G46+G56 -> 7136.4 | H57: =H46+H56 -> 8318.22 | I57: =I46+I56 -> 8986.23 | J57: =J46+J56 -> 14176.967 | K57: =K46+K56 -> 14977.569 | L57: =L46+L56 -> 16884.952 | ... N57: =N46+N56 -> 19560.789
B58: Total Equity and Liabilities | E58: =E57+E37 -> 23096.09 | F58: =F57+F37 -> 22478.39 | G58: =G57+G37 -> 23917.03 | H58: =H57+H37 -> 26152.79 | I58: =I57+I37 -> 28390.32 | J58: =J57+J37 -> 38813.541 | K58: =K57+K37 -> 45637.547 | L58: =L57+L37 -> 54095.604 | ... N58: =N57+N37 -> 71948.184
B62: Balancing Check | E62: =E58-E31 -> 0 | F62: =F58-F31 -> 0 | G62: =G58-G31 -> 0 | H62: =H58-H31 -> 0 | I62: =I58-I31 -> 0 | J62: =J58-J31 -> 0 | K62: =K58-K31 -> 0 | L62: =L58-L31 -> 0 | ... N62: =N58-N31 -> 0

Sheet P&L
B2: Particulars | C2: Notes | E2: FY21 | F2: FY22 | G2: FY23 | H2: FY24 | I2: FY25 | J2: FY26E | K2: FY27E | L2: FY28E | M2: FY29E | N2: FY30E
B4: Income
A5: Revenue Model | B5: Revenue from Operations | E5: 30959.19 | F5: 29551.28 | G5: 34158.38 | H5: 37788.62 | I5: 40923.42 | J5: ='Revenue Model'!J19 -> 47095.708 | K5: ='Revenue Model'!K19 -> 52303.558 | L5: ='Revenue Model'!L19 -> 57893.45 | M5: ='Revenue Model'!M19 -> 63992.396 | N5: ='Revenue Model'!N19 -> 70423.32
A6: Assumptions | B6: Other Income | E6: 557.9 | F6: 555.01 | G6: 569.01 | H6: 854.54 | I6: 1044.08 | J6: =Assumptions!J5 -> 1412.8712 | K6: =Assumptions!K5 -> 1569.1067 | L6: =Assumptions!L5 -> 1736.8035 | M6: =Assumptions!M5 -> 1919.7719 | N6: =Assumptions!N5 -> 2112.6996
B7: Total Income | E7: =E5+E6 -> 31517.09 | F7: =F5+F6 -> 30106.29 | G7: =G5+G6 -> 34727.39 | H7: =H5+H6 -> 38643.16 | I7: =I5+I6 -> 41967.5 | J7: =J5+J6 -> 48508.58 | K7: =K5+K6 -> 53872.664 | L7: =L5+L6 -> 59630.253 | ... N7: =N5+N6 -> 72536.02
B8: Expenses
A9: Assumptions | B9: Cost of materials consumed | E9: 21968.04 | F9: 20845.74 | G9: 24060.29 | H9: 24836.89 | I9: 26607.07 | J9: =Assumptions!J11 -> 31491.028 | K9: =Assumptions!K11 -> 34750.663 | L9: =Assumptions!L11 -> 38332.339 | M9: =Assumptions!M11 -> 42421.667 | N9: =Assumptions!N11 -> 46729.342
A10: Assumptions | B10: Purchase of Stock-in-trade | E10: 31.14 | F10: 45.95 | G10: 47.43 | H10: 484.2 | I10: 547.91 | J10: =Assumptions!J13 -> 617.00199 | K10: =Assumptions!K13 -> 692.7525 | L10: =Assumptions!L13 -> 762.6266 | M10: =Assumptions!M13 -> 845.26849 | N10: =Assumptions!N13 -> 928.94781
A11: Assumptions | B11: Change in inventories of finished goods, stock-in-trade and work-in-progress | E11: -255.57 | F11: 28.67 | G11: -163.69 | H11: 188.35 | I11: -244.34 | J11: =Assumptions!J15 -> 3.2614623 | K11: =Assumptions!K15 -> -204.29838 | L11: =Assumptions!L15 -> -15.795035 | M11: =Assumptions!M15 -> -235.6662 | N11: =Assumptions!N15 -> -29.018167
A12: Assumptions | B12: Employee Benefits Expense | E12: 1951.02 | F12: 1995.78 | G12: 2250.05 | H12: 2471.55 | I12: 2680.07 | J12: =Assumptions!J16 -> 3083.0814 | K12: =Assumptions!K16 -> 3449.5862 | L12: =Assumptions!L16 -> 3799.9286 | M12: =Assumptions!M16 -> 4197.2413 | N12: =Assumptions!N16 -> 4621.6503
A13: Debt Schedule | B13: Finance Costs | E13: 46.41 | F13: 53.1 | G13: 104.88 | H13: 76.37 | I13: 70.65 | J13: ='Schedule Populated '!J61 -> 81.949969 | K13: ='Schedule Populated '!K61 -> 95.680508 | L13: ='Schedule Populated '!L61 -> 111.97452 | M13: ='Schedule Populated '!M61 -> 111.88428 | N13: ='Schedule Populated '!N61 -> 121.23216
A14: Capex Schedule | B14: Depreciation and Amortisation Expense | E14: 715.12 | F14: 689.52 | G14: 697.39 | H14: 757.36 | I14: 824.59 | J14: ='Schedule Populated '!J28 -> 845.69632 | K14: ='Schedule Populated '!K28 -> 913.30015 | L14: ='Schedule Populated '!L28 -> 998.76173 | M14: ='Schedule Populated '!M28 -> 1094.7435 | N14: ='Schedule Populated '!N28 -> 1193.6248
A15: Assumptions | B15: Other Expenses | E15: 3165.05 | F15: 3190.37 | G15: 3870.53 | H15: 4458 | I15: 5386.87 | J15: =Assumptions!J18 -> 5398.2013 | K15: =Assumptions!K18 -> 6124.7325 | L15: =Assumptions!L18 -> 6885.1281 | M15: =Assumptions!M18 -> 7682.3411 | N15: =Assumptions!N18 -> 8483.6584
B16: Total Expenses | E16: =SUM(E9:E15) -> 27621.21 | F16: =SUM(F9:F15) -> 26849.13 | G16: =SUM(G9:G15) -> 30866.88 | H16: =SUM(H9:H15) -> 33272.72 | I16: =SUM(I9:I15) -> 35872.82 | J16: =SUM(J9:J15) -> 41520.221 | K16: =SUM(K9:K15) -> 45822.417 | L16: =SUM(L9:L15) -> 50874.963 | ... N16: =SUM(N9:N15) -> 62049.438
B17: Profit before tax and exceptional items | E17: 3849.32 | F17: 3058.11 | G17: 3863.62 | H17: 5250.19 | I17: 5933.56 | J17: =J7-J16 -> 6988.3588 | K17: =K7-K16 -> 8050.2477 | L17: =L7-L16 -> 8755.2898 | M17: =M7-M16 -> 9794.6883 | N17: =N7-N16 -> 10486.582
A18: Assumptions | B18: Exceptional item | E18: 0 | F18: 0 | G18: 0 | H18: 159.99 | I18: 0 | J18: =Assumptions!J20 -> 0 | K18: =Assumptions!K20 -> 0 | L18: =Assumptions!L20 -> 0 | M18: =Assumptions!M20 -> 0 | N18: =Assumptions!N20 -> 0
A19: Assumptions | B19: Profit before tax | E19: =E17-E18 -> 3849.32 | F19: =F17-F18 -> 3058.11 | G19: =G17-G18 -> 3863.62 | H19: =H17-H18 -> 5090.2 | I19: =I17-I18 -> 5933.56 | J19: =J17-J18 -> 6988.3588 | K19: =K17-K18 -> 8050.2477 | L19: =L17-L18 -> 8755.2898 | ... N19: =N17-N18 -> 10486.582
B20: Tax expense
B21: i) Current tax | E21: 931.38 | F21: 805.44 | G21: 947.69 | H21: 1264.18 | I21: 1448.02
B22: ii) Deferred tax charge | E22: -18.11 | F22: -76.38 | G22: 116.03 | H22: 83.86 | I22: 109.73
B23: Total tax expense | E23: =E21+E22 -> 913.27 | F23: =F21+F22 -> 729.06 | G23: =G21+G22 -> 1063.72 | H23: =H21+H22 -> 1348.04 | I23: =I21+I22 -> 1557.75 | J23: =Assumptions!J23 -> 1758.9699 | K23: =Assumptions!K23 -> 2026.2473 | L23: =Assumptions!L23 -> 2203.7064 | M23: =Assumptions!M23 -> 2465.323 | N23: =Assumptions!N23 -> 2639.4727
B24: Net profit after taxes | E24: =E19-E23 -> 2936.05 | F24: =F19-F23 -> 2329.05 | G24: =G19-G23 -> 2799.9 | H24: =H19-H23 -> 3742.16 | I24: =I19-I23 -> 4375.81 | J24: =J19-J23 -> 5229.3889 | K24: =K19-K23 -> 6024.0004 | L24: =L19-L23 -> 6551.5833 | ... N24: =N19-N23 -> 7847.1095
B26: EBIT | E26: =E19+E13 -> 3895.73 | F26: =F19+F13 -> 3111.21 | G26: =G19+G13 -> 3968.5 | H26: =H19+H13 -> 5166.57 | I26: =I19+I13 -> 6004.21 | J26: =J19+J13 -> 7070.3087 | K26: =K19+K13 -> 8145.9282 | L26: =L19+L13 -> 8867.2643 | ... N26: =N19+N13 -> 10607.814

Sheet CFS
B2: Particulars | C2: Notes | E2: FY26E | F2: FY27E | G2: FY28E | H2: FY29E | I2: FY30E
B3: Net Profit | E3: ='P&L'!J24 -> 5229.3889 | F3: ='P&L'!K24 -> 6024.0004 | G3: ='P&L'!L24 -> 6551.5833 | H3: ='P&L'!M24 -> 7329.3652 | I3: ='P&L'!N24 -> 7847.1095
B4: Add Finance Costs | E4: ='P&L'!J13 -> 81.949969 | F4: ='P&L'!K13 -> 95.680508 | G4: ='P&L'!L13 -> 111.97452 | H4: ='P&L'!M13 -> 111.88428 | I4: ='P&L'!N13 -> 121.23216
B5: Add Depreciation | E5: ='P&L'!J14 -> 845.69632 | F5: ='P&L'!K14 -> 913.30015 | G5: ='P&L'!L14 -> 998.76173 | H5: ='P&L'!M14 -> 1094.7435 | I5: ='P&L'!N14 -> 1193.6248
B6: Less Change in Net Working Capital | E6: =-'Schedule Populated '!J102 -> 4188.1265 | F6: =-'Schedule Populated '!K102 -> -872.60736 | G6: =-'Schedule Populated '!L102 -> 655.56167 | H6: =-'Schedule Populated '!M102 -> -488.67789 | I6: =-'Schedule Populated '!N102 -> -834.8911
B7: Cash Flow from Operating Activities | E7: =SUM(E3:E6) -> 10345.162 | F7: =SUM(F3:F6) -> 6160.3737 | G7: =SUM(G3:G6) -> 8317.8812 | H7: =SUM(H3:H6) -> 8047.3151 | I7: =SUM(I3:I6) -> 8327.0753
B9: Change in Investments | E9: =SUM('Balance Sheet '!I6,'Balance Sheet '!I9:I10,'Balance Sheet '!I12:I16,'Balance Sheet '!J43:J45)-SUM('Balance Sheet '!J6,'Balance Sheet '!J9:J10,'Balance Sheet '!J12:J16,'Balance Sheet '!I43:I45) -> 154.56 | F9: =SUM('Balance Sheet '!J6,'Balance Sheet '!J9:J10,'Balance Sheet '!J12:J16,'Balance Sheet '!K43:K45)-SUM('Balance Sheet '!K6,'Balance Sheet '!K9:K10,'Balance Sheet '!K12:K16,'Balance Sheet '!J43:J45) -> 17.972 | G9: =SUM('Balance Sheet '!K6,'Balance Sheet '!K9:K10,'Balance Sheet '!K12:K16,'Balance Sheet '!L43:L45)-SUM('Balance Sheet '!L6,'Balance Sheet '!L9:L10,'Balance Sheet '!L12:L16,'Balance Sheet '!K43:K45) -> -182.5592 | H9: =SUM('Balance Sheet '!L6,'Balance Sheet '!L9:L10,'Balance Sheet '!L12:L16,'Balance Sheet '!M43:M45)-SUM('Balance Sheet '!M6,'Balance Sheet '!M9:M10,'Balance Sheet '!M12:M16,'Balance Sheet '!L43:L45) -> -44.26908 | I9: =SUM('Balance Sheet '!M6,'Balance Sheet '!M9:M10,'Balance Sheet '!M12:M16,'Balance Sheet '!N43:N45)-SUM('Balance Sheet '!N6,'Balance Sheet '!N9:N10,'Balance Sheet '!N12:N16,'Balance Sheet '!M43:M45) -> 62.278808
B10: Capital Expenditure | E10: =-'Schedule Populated '!J40 -> -1484.262 | F10: =-'Schedule Populated '!K40 -> -1522.2534 | G10: =-'Schedule Populated '!L40 -> -1643.9403 | H10: =-'Schedule Populated '!M40 -> -1797.7711 | I10: =-'Schedule Populated '!N40 -> -1970.5383
B11: Cash Flow from Investing Activities | E11: =SUM(E9:E10) -> -1329.702 | F11: =SUM(F9:F10) -> -1504.2814 | G11: =SUM(G9:G10) -> -1826.4995 | H11: =SUM(H9:H10) -> -1842.0402 | I11: =SUM(I9:I10) -> -1908.2595
B13: Changes to Equity | E13: 0 | F13: 0 | G13: 0 | H13: 0 | I13: 0
B14: Changes in Non-Controlling Interest | E14: =Assumptions!J39-Assumptions!I39 -> 3.095 | F14: =Assumptions!K39-Assumptions!J39 -> -0.596 | G14: =Assumptions!L39-Assumptions!K39 -> -0.9099 | H14: =Assumptions!M39-Assumptions!L39 -> 0.46574 | I14: =Assumptions!N39-Assumptions!M39 -> -0.196774
B15: Net Loans Raised for the long term | E15: ='Schedule Populated '!J68+'Schedule Populated '!J73 -> 10.815 | F15: ='Schedule Populated '!K68+'Schedule Populated '!K73 -> 10.301025 | G15: ='Schedule Populated '!L68+'Schedule Populated '!L73 -> 10.816076 | H15: ='Schedule Populated '!M68+'Schedule Populated '!M73 -> 11.407105 | I15: ='Schedule Populated '!N68+'Schedule Populated '!N73 -> 11.974949
B16: Finance Costs Paid | E16: =-'Schedule Populated '!J61 -> -81.949969 | F16: =-'Schedule Populated '!K61 -> -95.680508 | G16: =-'Schedule Populated '!L61 -> -111.97452 | H16: =-'Schedule Populated '!M61 -> -111.88428 | I16: =-'Schedule Populated '!N61 -> -121.23216
B17: Dividend Paid | E17: 0 | F17: 0 | G17: 0 | H17: 0 | I17: 0
B18: Cash Flow from Financing Activities | E18: =SUM(E13:E17) -> -68.039969 | F18: =SUM(F13:F17) -> -85.975483 | G18: =SUM(G13:G17) -> -102.06835 | H18: =SUM(H13:H17) -> -100.01143 | I18: =SUM(I13:I17) -> -109.45399
B20: Total Cash Flow | E20: =E18+E11+E7 -> 8947.4197 | F20: =F18+F11+F7 -> 4570.1168 | G20: =G18+G11+G7 -> 6389.3134 | H20: =H18+H11+H7 -> 6105.2635 | I20: =I18+I11+I7 -> 6309.3619
B21: Beginning Cash Balance | E21: ='Balance Sheet '!I24 -> 574.08 | F21: ='Balance Sheet '!J24 -> 9521.4997 | G21: ='Balance Sheet '!K24 -> 14091.617 | H21: ='Balance Sheet '!L24 -> 20480.93 | I21: ='Balance Sheet '!M24 -> 26586.193
B22: Closing Cash Balance in Balance Sheet | E22: =SUM(E20:E21) -> 9521.4997 | F22: =SUM(F20:F21) -> 14091.617 | G22: =SUM(G20:G21) -> 20480.93 | H22: =SUM(H20:H21) -> 26586.193 | I22: =SUM(I20:I21) -> 32895.555

Sheet Assumptions
B2: Revenue Assumptions | C2: Notes | E2: FY21 | F2: FY22 | G2: FY23 | H2: FY24 | I2: FY25 | J2: FY26E | K2: FY27E | L2: FY28E | M2: FY29E | N2: FY30E
B4: Revenue | E4: ='P&L'!E5 -> 30959.19 | F4: ='P&L'!F5 -> 29551.28 | G4: ='P&L'!G5 -> 34158.38 | H4: ='P&L'!H5 -> 37788.62 | I4: ='P&L'!I5 -> 40923.42 | J4: ='P&L'!J5 -> 47095.708 | K4: ='P&L'!K5 -> 52303.558 | L4: ='P&L'!L5 -> 57893.45 | ... N4: ='P&L'!N5 -> 70423.32
B5: Other Income | E5: ='P&L'!E6 -> 557.9 | F5: ='P&L'!F6 -> 555.01 | G5: ='P&L'!G6 -> 569.01 | H5: ='P&L'!H6 -> 854.54 | I5: ='P&L'!I6 -> 1044.08 | J5: =J6*J4 -> 1412.8712 | K5: =K6*K4 -> 1569.1067 | L5: =L6*L4 -> 1736.8035 | M5: =M6*M4 -> 1919.7719 | N5: =N6*N4 -> 2112.6996
B6: As a% of Total Revenue | E6: =E5/E4 -> 0.018020497 | F6: =F5/F4 -> 0.018781251 | G6: =G5/G4 -> 0.016657991 | H6: =H5/H4 -> 0.022613686 | I6: =I5/I4 -> 0.025513019 | J6: 0.03 | K6: 0.03 | L6: 0.03 | M6: 0.03 | N6: 0.03
B7: Total | E7: =E4+E5 -> 31517.09 | F7: =F4+F5 -> 30106.29 | G7: =G4+G5 -> 34727.39 | H7: =H4+H5 -> 38643.16 | I7: =I4+I5 -> 41967.5 | J7: =J4+J5 -> 48508.58 | K7: =K4+K5 -> 53872.664 | L7: =L4+L5 -> 59630.253 | ... N7: =N4+N5 -> 72536.02
B9: Other P&L Assumptions | C9: Notes | E9: FY21 | F9: FY22 | G9: FY23 | H9: FY24 | I9: FY25 | J9: FY26E | K9: FY27E | L9: FY28E | M9: FY29E | N9: FY30E
B11: Cost of materials consumed | E11: ='P&L'!E9 -> 21968.04 | F11: ='P&L'!F9 -> 20845.74 | G11: ='P&L'!G9 -> 24060.29 | H11: ='P&L'!H9 -> 24836.89 | I11: ='P&L'!I9 -> 26607.07 | J11: =J12*J4 -> 31491.028 | K11: =K12*K4 -> 34750.663 | L11: =L12*L4 -> 38332.339 | M11: =M12*M4 -> 42421.667 | N11: =N12*N4 -> 46729.342
B12: As a% of Revenue | E12: =E11/E4 -> 0.70958058 | F12: =F11/F4 -> 0.70540904 | G12: =G11/G4 -> 0.70437445 | H12: =H11/H4 -> 0.65725846 | I12: =I11/I4 -> 0.65016731 | J12: =40%*I12+30%*H12+20%*G12+10%*F12 -> 0.66866025 | K12: =40%*J12+30%*I12+20%*H12+10%*G12 -> 0.66440343 | L12: =40%*K12+30%*J12+20%*I12+10%*H12 -> 0.66211876 | M12: =40%*L12+30%*K12+20%*J12+10%*I12 -> 0.66291731 | N12: =40%*M12+30%*L12+20%*K12+10%*J12 -> 0.66354926
B13: Purchase of Stock-in-trade | E13: ='P&L'!E10 -> 31.14 | F13: ='P&L'!F10 -> 45.95 | G13: ='P&L'!G10 -> 47.43 | H13: ='P&L'!H10 -> 484.2 | I13: ='P&L'!I10 -> 547.91 | J13: =J14*J4 -> 617.00199 | K13: =K14*K4 -> 692.7525 | L13: =L14*L4 -> 762.6266 | M13: =M14*M4 -> 845.26849 | N13: =N14*N4 -> 928.94781
B14: As a% of Revenue | E14: =E13/E4 -> 0.0010058403 | F14: =F13/F4 -> 0.0015549242 | G14: =G13/G4 -> 0.0013885319 | H14: =H13/H4 -> 0.012813381 | I14: =I13/I4 -> 0.013388666 | J14: =AVERAGE(H14:I14) -> 0.013101024 | K14: =AVERAGE(I14:J14) -> 0.013244845 | L14: =AVERAGE(J14:K14) -> 0.013172934 | M14: =AVERAGE(K14:L14) -> 0.01320889 | N14: =AVERAGE(L14:M14) -> 0.013190912
B15: Change in inventories of finished goods, stock-in-trade and work-in-progress | E15: ='P&L'!E11 -> -255.57 | F15: ='P&L'!F11 -> 28.67 | G15: ='P&L'!G11 -> -163.69 | H15: ='P&L'!H11 -> 188.35 | I15: ='P&L'!I11 -> -244.34 | J15: =J55 -> 3.2614623 | K15: =K55 -> -204.29838 | L15: =L55 -> -15.795035 | M15: =M55 -> -235.6662 | N15: =N55 -> -29.018167
B16: Employee Benefits Expense | E16: ='P&L'!E12 -> 1951.02 | F16: ='P&L'!F12 -> 1995.78 | G16: ='P&L'!G12 -> 2250.05 | H16: ='P&L'!H12 -> 2471.55 | I16: ='P&L'!I12 -> 2680.07 | J16: =J17*J4 -> 3083.0814 | K16: =K17*K4 -> 3449.5862 | L16: =L17*L4 -> 3799.9286 | M16: =M17*M4 -> 4197.2413 | N16: =N17*N4 -> 4621.6503
B17: As a% of Revenue | E17: =E16/E4 -> 0.063019091 | F17: =F16/F4 -> 0.067536161 | G17: =G16/G4 -> 0.065871098 | H17: =H16/H4 -> 0.065404611 | I17: =I16/I4 -> 0.065489883 | J17: =AVERAGE(E17:I17) -> 0.065464169 | K17: =AVERAGE(F17:J17) -> 0.065953184 | L17: =AVERAGE(G17:K17) -> 0.065636589 | M17: =AVERAGE(H17:L17) -> 0.065589687 | N17: =AVERAGE(I17:M17) -> 0.065626703
B18: Other Expenses | E18: ='P&L'!E15 -> 3165.05 | F18: ='P&L'!F15 -> 3190.37 | G18: ='P&L'!G15 -> 3870.53 | H18: ='P&L'!H15 -> 4458 | I18: ='P&L'!I15 -> 5386.87 | J18: =J19*J4 -> 5398.2013 | K18: =K19*K4 -> 6124.7325 | L18: =L19*L4 -> 6885.1281 | M18: =M19*M4 -> 7682.3411 | N18: =N19*N4 -> 8483.6584
B19: As a% of Revenue | E19: =E18/E4 -> 0.10223297 | F19: =F18/F4 -> 0.10796047 | G19: =G18/G4 -> 0.11331129 | H19: =H18/H4 -> 0.11797202 | I19: =I18/I4 -> 0.13163294 | J19: =AVERAGE(E19:I19) -> 0.11462194 | K19: =AVERAGE(F19:J19) -> 0.11709973 | L19: =AVERAGE(G19:K19) -> 0.11892758 | M19: =AVERAGE(H19:L19) -> 0.12005084 | N19: =AVERAGE(I19:M19) -> 0.12046661
B20: Exceptional item | E20: ='P&L'!E18 -> 0 | F20: ='P&L'!F18 -> 0 | G20: ='P&L'!G18 -> 0 | H20: ='P&L'!H18 -> 159.99 | I20: ='P&L'!I18 -> 0 | J20: 0 | K20: 0 | L20: 0 | M20: 0 | N20: 0
B21: Profit before tax | E21: ='P&L'!E19 -> 3849.32 | F21: ='P&L'!F19 -> 3058.11 | G21: ='P&L'!G19 -> 3863.62 | H21: ='P&L'!H19 -> 5090.2 | I21: ='P&L'!I19 -> 5933.56 | J21: ='P&L'!J19 -> 6988.3588 | K21: ='P&L'!K19 -> 8050.2477 | L21: ='P&L'!L19 -> 8755.2898 | ... N21: ='P&L'!N19 -> 10486.582
B22: Tax Rate | J22: 0.2517 | K22: 0.2517 | L22: 0.2517 | M22: 0.2517 | N22: 0.2517
B23: Tax Expense | J23: =J22*J21 -> 1758.9699 | K23: =K22*K21 -> 2026.2473 | L23: =L22*L21 -> 2203.7064 | M23: =M22*M21 -> 2465.323 | N23: =N22*N21 -> 2639.4727
B25: Other Balance Sheet Assumptions | C25: Notes | E25: FY21 | F25: FY22 | G25: FY23 | H25: FY24 | I25: FY25 | J25: FY26E | K25: FY27E | L25: FY28E | M25: FY29E | N25: FY30E
B27: Capital work-in-progress | E27: ='Balance Sheet '!E6 -> 236.4 | F27: ='Balance Sheet '!F6 -> 149.13 | G27: ='Balance Sheet '!G6 -> 122.09 | H27: ='Balance Sheet '!H6 -> 127.16 | I27: ='Balance Sheet '!I6 -> 105.37 | J27: =I27*40%+H27*30%+G27*10%+F27*10%+E27*10% -> 131.058 | K27: =J27*40%+I27*30%+H27*10%+G27*10%+F27*10% -> 123.8722 | L27: =K27*40%+J27*30%+I27*10%+H27*10%+G27*10% -> 124.32828 | M27: =L27*40%+K27*30%+J27*10%+I27*10%+H27*10% -> 123.25177 | N27: =M27*40%+L27*30%+K27*10%+J27*10%+I27*10% -> 122.62921
B28: Intangible assets under development | E28: ='Balance Sheet '!E9 -> 258.73 | F28: ='Balance Sheet '!F9 -> 368.09 | G28: ='Balance Sheet '!G9 -> 331.62 | H28: ='Balance Sheet '!H9 -> 356.9 | I28: ='Balance Sheet '!I9 -> 381.81 | J28: =I28*40%+H28*30%+G28*10%+F28*10%+E28*10% -> 355.638 | K28: =J28*40%+I28*30%+H28*10%+G28*10%+F28*10% -> 362.4592 | L28: =K28*40%+J28*30%+I28*10%+H28*10%+G28*10% -> 358.70808 | M28: =L28*40%+K28*30%+J28*10%+I28*10%+H28*10% -> 361.65579 | N28: =M28*40%+L28*30%+K28*10%+J28*10%+I28*10% -> 362.26546
B29: Equity accounted investments in associates | E29: ='Balance Sheet '!E10 -> 2407.69 | F29: ='Balance Sheet '!F10 -> 2202.51 | G29: ='Balance Sheet '!G10 -> 2618.7 | H29: ='Balance Sheet '!H10 -> 3083.59 | I29: ='Balance Sheet '!I10 -> 2980.94 | J29: =I29*40%+H29*30%+G29*10%+F29*10%+E29*10% -> 2840.343 | K29: =J29*40%+I29*30%+H29*10%+G29*10%+F29*10% -> 2820.8992 | L29: =K29*40%+J29*30%+I29*10%+H29*10%+G29*10% -> 2848.7856 | M29: =L29*40%+K29*30%+J29*10%+I29*10%+H29*10% -> 2876.2713 | N29: =M29*40%+L29*30%+K29*10%+J29*10%+I29*10% -> 2869.3624
B30: Financial Assets
B31: i) Investments | E31: ='Balance Sheet '!E12 -> 1948.59 | F31: ='Balance Sheet '!F12 -> 2455.05 | G31: ='Balance Sheet '!G12 -> 4600.38 | H31: ='Balance Sheet '!H12 -> 5362.57 | I31: ='Balance Sheet '!I12 -> 4767.33 | J31: =I31*40%+H31*30%+G31*10%+F31*10%+E31*10% -> 4416.105 | K31: =J31*40%+I31*30%+H31*10%+G31*10%+F31*10% -> 4438.441 | L31: =K31*40%+J31*30%+I31*10%+H31*10%+G31*10% -> 4573.2359 | M31: =L31*40%+K31*30%+J31*10%+I31*10%+H31*10% -> 4615.4272 | N31: =M31*40%+L31*30%+K31*10%+J31*10%+I31*10% -> 4580.3292
B32: ii) Loans | E32: ='Balance Sheet '!E13 -> 16.73 | F32: ='Balance Sheet '!F13 -> 17.43 | G32: ='Balance Sheet '!G13 -> 19.87 | H32: ='Balance Sheet '!H13 -> 21.15 | I32: ='Balance Sheet '!I13 -> 24.87 | J32: =I32*40%+H32*30%+G32*10%+F32*10%+E32*10% -> 21.696 | K32: =J32*40%+I32*30%+H32*10%+G32*10%+F32*10% -> 21.9844 | L32: =K32*40%+J32*30%+I32*10%+H32*10%+G32*10% -> 21.89156 | M32: =L32*40%+K32*30%+J32*10%+I32*10%+H32*10% -> 22.123544 | N32: =M32*40%+L32*30%+K32*10%+J32*10%+I32*10% -> 22.271926
B33: iii) Others | E33: ='Balance Sheet '!E14 -> 35.91 | F33: ='Balance Sheet '!F14 -> 42.01 | G33: ='Balance Sheet '!G14 -> 206.09 | H33: ='Balance Sheet '!H14 -> 189.44 | I33: ='Balance Sheet '!I14 -> 47.09 | J33: =I33*40%+H33*30%+G33*10%+F33*10%+E33*10% -> 104.069 | K33: =J33*40%+I33*30%+H33*10%+G33*10%+F33*10% -> 99.5086 | L33: =K33*40%+J33*30%+I33*10%+H33*10%+G33*10% -> 115.28614 | M33: =L33*40%+K33*30%+J33*10%+I33*10%+H33*10% -> 110.02694 | N33: =M33*40%+L33*30%+K33*10%+J33*10%+I33*10% -> 103.66338
B34: Income Tax Assets (Net) | E34: ='Balance Sheet '!E15 -> 378.49 | F34: ='Balance Sheet '!F15 -> 358.07 | G34: ='Balance Sheet '!G15 -> 270.69 | H34: ='Balance Sheet '!H15 -> 335.68 | I34: ='Balance Sheet '!I15 -> 254.49 | J34: =I34*40%+H34*30%+G34*10%+F34*10%+E34*10% -> 303.225 | K34: =J34*40%+I34*30%+H34*10%+G34*10%+F34*10% -> 294.081 | L34: =K34*40%+J34*30%+I34*10%+H34*10%+G34*10% -> 294.6859 | M34: =L34*40%+K34*30%+J34*10%+I34*10%+H34*10% -> 295.43816 | N34: =M34*40%+L34*30%+K34*10%+J34*10%+I34*10% -> 291.76063
B35: Other Non-current Assets | E35: ='Balance Sheet '!E16 -> 62.68 | F35: ='Balance Sheet '!F16 -> 120.34 | G35: ='Balance Sheet '!G16 -> 153.06 | H35: ='Balance Sheet '!H16 -> 128.65 | I35: ='Balance Sheet '!I16 -> 111.55 | J35: =I35*40%+H35*30%+G35*10%+F35*10%+E35*10% -> 116.823 | K35: =J35*40%+I35*30%+H35*10%+G35*10%+F35*10% -> 120.3992 | L35: =K35*40%+J35*30%+I35*10%+H35*10%+G35*10% -> 122.53258 | M35: =L35*40%+K35*30%+J35*10%+I35*10%+H35*10% -> 120.83509 | N35: =M35*40%+L35*30%+K35*10%+J35*10%+I35*10% -> 119.97103
B36: Equity
B37: i) Equity Share Capital | E37: ='Balance Sheet '!E34 -> 39.96 | F37: ='Balance Sheet '!F34 -> 39.96 | G37: ='Balance Sheet '!G34 -> 39.97 | H37: ='Balance Sheet '!H34 -> 39.98 | I37: ='Balance Sheet '!I34 -> 40 | J37: 40 | K37: 40 | L37: 40 | M37: 40 | N37: 40
B38: iii) Other Equity | E38: ='Balance Sheet '!E35 -> 15376.46 | F38: ='Balance Sheet '!F35 -> 15806.69 | G38: ='Balance Sheet '!G35 -> 16615.6 | H38: ='Balance Sheet '!H35 -> 17658.94 | I38: ='Balance Sheet '!I35 -> 19232.04 | J38: =I38+'P&L'!J24 -> 24461.429 | K38: =J38+'P&L'!K24 -> 30485.429 | L38: =K38+'P&L'!L24 -> 37037.013 | M38: =L38+'P&L'!M24 -> 44366.378 | N38: =M38+'P&L'!N24 -> 52213.487
B39: Non - Controlling Interests | E39: ='Balance Sheet '!E36 -> 143.19 | F39: ='Balance Sheet '!F36 -> 148.05 | G39: ='Balance Sheet '!G36 -> 125.06 | H39: ='Balance Sheet '!H36 -> 135.65 | I39: ='Balance Sheet '!I36 -> 132.05 | J39: =I39*40%+H39*30%+G39*10%+F39*10%+E39*10% -> 135.145 | K39: =J39*40%+I39*30%+H39*10%+G39*10%+F39*10% -> 134.549 | L39: =K39*40%+J39*30%+I39*10%+H39*10%+G39*10% -> 133.6391 | M39: =L39*40%+K39*30%+J39*10%+I39*10%+H39*10% -> 134.10484 | N39: =M39*40%+L39*30%+K39*10%+J39*10%+I39*10% -> 133.90807
B41: Other Financial Liabilities | E41: ='Balance Sheet '!E43 -> 146.04 | F41: ='Balance Sheet '!F43 -> 155.04 | G41: ='Balance Sheet '!G43 -> 196.29 | H41: ='Balance Sheet '!H43 -> 178.13 | I41: ='Balance Sheet '!I43 -> 143.83 | J41: =I41*40%+H41*30%+G41*10%+F41*10%+E41*10% -> 160.708 | K41: =J41*40%+I41*30%+H41*10%+G41*10%+F41*10% -> 160.3782 | L41: =K41*40%+J41*30%+I41*10%+H41*10%+G41*10% -> 164.18868 | M41: =L41*40%+K41*30%+J41*10%+I41*10%+H41*10% -> 162.05573 | N41: =M41*40%+L41*30%+K41*10%+J41*10%+I41*10% -> 160.57052
B42: Provisions | E42: ='Balance Sheet '!E44 -> 175.57 | F42: ='Balance Sheet '!F44 -> 181.13 | G42: ='Balance Sheet '!G44 -> 201.94 | H42: ='Balance Sheet '!H44 -> 322.46 | I42: ='Balance Sheet '!I44 -> 495.29 | J42: =I42*40%+H42*30%+G42*10%+F42*10%+E42*10% -> 350.718 | K42: =J42*40%+I42*30%+H42*10%+G42*10%+F42*10% -> 359.4272 | L42: =K42*40%+J42*30%+I42*10%+H42*10%+G42*10% -> 350.95528 | M42: =L42*40%+K42*30%+J42*10%+I42*10%+H42*10% -> 365.05707 | N42: =M42*40%+L42*30%+K42*10%+J42*10%+I42*10% -> 371.85293
B43: Deferred Tax Liabilities (Net) | E43: ='Balance Sheet '!E45 -> 452.74 | F43: ='Balance Sheet '!F45 -> 378.21 | G43: ='Balance Sheet '!G45 -> 485.79 | H43: ='Balance Sheet '!H45 -> 570.13 | I43: ='Balance Sheet '!I45 -> 674.92 | J43: =I43*40%+H43*30%+G43*10%+F43*10%+E43*10% -> 572.681 | K43: =J43*40%+I43*30%+H43*10%+G43*10%+F43*10% -> 574.9614 | L43: =K43*40%+J43*30%+I43*10%+H43*10%+G43*10% -> 574.87286 | M43: =L43*40%+K43*30%+J43*10%+I43*10%+H43*10% -> 584.21066 | N43: =M43*40%+L43*30%+K43*10%+J43*10%+I43*10% -> 588.40236
B51: Other Balance Sheet Assumptions | C51: Notes | E51: FY21 | F51: FY22 | G51: FY23 | H51: FY24 | I51: FY25 | J51: FY26E | K51: FY27E | L51: FY28E | M51: FY29E | N51: FY30E
B53: Opening Inventory | E53: 522.69 | F53: 778.26 | G53: 749.59 | H53: 913.28 | I53: 724.93 | J53: =I54 -> 969.27 | K53: =J54 -> 966.00854 | L53: =K54 -> 1170.3069 | M53: =L54 -> 1186.102 | N53: =M54 -> 1421.7682
B54: Closing Inventory | E54: 778.26 | F54: 749.59 | G54: 913.28 | H54: 724.93 | I54: 969.27 | J54: =(2*J57)-J53 -> 966.00854 | K54: =(2*K57)-K53 -> 1170.3069 | L54: =(2*L57)-L53 -> 1186.102 | M54: =(2*M57)-M53 -> 1421.7682 | N54: =(2*N57)-N53 -> 1450.7863
B55: Net inc/dec in Inventory | E55: =E53-E54 -> -255.57 | F55: =F53-F54 -> 28.67 | G55: =G53-G54 -> -163.69 | H55: =H53-H54 -> 188.35 | I55: =I53-I54 -> -244.34 | J55: =J53-J54 -> 3.2614623 | K55: =K53-K54 -> -204.29838 | L55: =L53-L54 -> -15.795035 | ... N55: =N53-N54 -> -29.018167
B56: COGS | E56: =E11+E13 -> 21999.18 | F56: =F11+F13 -> 20891.69 | G56: =G11+G13 -> 24107.72 | H56: =H11+H13 -> 25321.09 | I56: =I11+I13 -> 27154.98 | J56: =J11+J13 -> 32108.03 | K56: =K11+K13 -> 35443.416 | L56: =L11+L13 -> 39094.965 | ... N56: =N11+N13 -> 47658.29
B57: Avg Inventory | E57: =AVERAGE(E53:E54) -> 650.475 | F57: =AVERAGE(F53:F54) -> 763.925 | G57: =AVERAGE(G53:G54) -> 831.435 | H57: =AVERAGE(H53:H54) -> 819.105 | I57: =AVERAGE(I53:I54) -> 847.1 | J57: =(J60/365)*J56 -> 967.63927 | K57: =(K60/365)*K56 -> 1068.1577 | L57: =(L60/365)*L56 -> 1178.2044 | M57: =(M60/365)*M56 -> 1303.9351 | N57: =(N60/365)*N56 -> 1436.2772
B60: Days Inventory Outstanding | E60: =(E57/E56)*365 -> 10.792374 | F60: =(F57/F56)*365 -> 13.346581 | G60: =(G57/G56)*365 -> 12.58824 | H60: =(H57/H56)*365 -> 11.807285 | I60: =(I57/I56)*365 -> 11.38618 | J60: 11 | K60: 11 | L60: 11 | M60: 11 | N60: 11

Sheet Revenue Model
B2: Particulars | C2: Notes | E2: FY21 | F2: FY22 | G2: FY23 | H2: FY24 | I2: FY25 | J2: FY26E | K2: FY27E | L2: FY28E | M2: FY29E | N2: FY30E
B4: Revenue from :-
B5: Sale of two wheelers | E5: 26823.27 | F5: 24275.42 | G5: 28400.38 | H5: 31326.34 | I5: 33906.58 | J5: =J34*J27 -> 39068.69 | K5: =K34*K27 -> 43456.094 | L5: =L34*L27 -> 47966.179 | M5: =M34*M27 -> 52899.763 | N5: =N34*N27 -> 58005.035
B6: YOY | E6: - | F6: =(F5-E5)/E5 -> -0.094986555 | G6: =(G5-F5)/F5 -> 0.16992332 | H6: =(H5-G5)/G5 -> 0.10302538 | I6: =(I5-H5)/H5 -> 0.082366469 | J6: =(J5-I5)/I5 -> 0.15224508 | K6: =(K5-J5)/J5 -> 0.11229976 | L6: =(L5-K5)/K5 -> 0.10378485 | M6: =(M5-L5)/L5 -> 0.10285547 | N6: =(N5-M5)/M5 -> 0.096508406
B7: Sale of spare parts | E7: 3199.17 | F7: 3933.75 | G7: 4899.8 | H7: 5829.83 | I7: 6389.97 | J7: =I7*(1+J8) -> 7303.389 | K7: =J7*(1+K8) -> 8176.2443 | L7: =K7*(1+L8) -> 9249.2106 | M7: =L7*(1+M8) -> 10408.8 | N7: =M7*(1+N8) -> 11744.257
B8: YOY | E8: - | F8: =(F7-E7)/E7 -> 0.22961581 | G8: =(G7-F7)/F7 -> 0.24557992 | H8: =(H7-G7)/G7 -> 0.18980979 | I8: =(I7-H7)/H7 -> 0.096081704 | J8: =AVERAGE(H8:I8) -> 0.14294575 | K8: =AVERAGE(I8:J8) -> 0.11951372 | L8: =AVERAGE(J8:K8) -> 0.13122974 | M8: =AVERAGE(K8:L8) -> 0.12537173 | N8: =AVERAGE(L8:M8) -> 0.12830073
B9: Total | C9: 1 | E9: =E5+E7 -> 30022.44 | F9: =F5+F7 -> 28209.17 | G9: =G5+G7 -> 33300.18 | H9: =H5+H7 -> 37156.17 | I9: =I5+I7 -> 40296.55 | J9: =J5+J7 -> 46372.079 | K9: =K5+K7 -> 51632.339 | L9: =L5+L7 -> 57215.389 | ... N9: =N5+N7 -> 69749.291
B11: Income from services
B12: Dealers support services | E12: 43.18 | F12: 86.81 | G12: 73.41 | H12: 75.04 | I12: 100.51 | J12: =AVERAGE(G12:I12) -> 82.986667 | K12: =AVERAGE(H12:J12) -> 86.178889 | L12: =AVERAGE(I12:K12) -> 89.891852 | M12: =AVERAGE(J12:L12) -> 86.352469 | N12: =AVERAGE(K12:M12) -> 87.474403
B13: Dealer / Customer Program | E13: 37.37 | F13: 50.52 | G13: 58.79 | H13: 42.43 | I13: 35.62 | J13: =AVERAGE(F13:I13) -> 46.84 | K13: =AVERAGE(G13:J13) -> 45.92 | L13: =AVERAGE(H13:K13) -> 42.7025 | M13: =AVERAGE(I13:L13) -> 42.770625 | N13: =AVERAGE(J13:M13) -> 44.558281
B14: Services - others | E14: 348.6 | F14: 341.24 | G14: 305.34 | H14: 325.39 | I14: 279.81 | J14: =AVERAGE(E14:I14) -> 320.076 | K14: =AVERAGE(F14:J14) -> 314.3712 | L14: =AVERAGE(G14:K14) -> 308.99744 | M14: =AVERAGE(H14:L14) -> 309.72893 | N14: =AVERAGE(I14:M14) -> 306.59671
B15: Total | C15: 2 | E15: =SUM(E12:E14) -> 429.15 | F15: =SUM(F12:F14) -> 478.57 | G15: =SUM(G12:G14) -> 437.54 | H15: =SUM(H12:H14) -> 442.86 | I15: =SUM(I12:I14) -> 415.94 | J15: =SUM(J12:J14) -> 449.90267 | K15: =SUM(K12:K14) -> 446.47009 | L15: =SUM(L12:L14) -> 441.59179 | ... N15: =SUM(N12:N14) -> 438.6294
B17: Other operating revenue | C17: 3 | E17: 507.6 | F17: 573.64 | G17: 420.66 | H17: 189.59 | I17: 210.93 | J17: =AVERAGE(G17:I17) -> 273.72667 | K17: =AVERAGE(H17:J17) -> 224.74889 | L17: =AVERAGE(I17:K17) -> 236.46852 | M17: =AVERAGE(J17:L17) -> 244.98136 | N17: =AVERAGE(K17:M17) -> 235.39959
B19: Revenue from operations (1+2+3) | E19: =E9+E17+E15 -> 30959.19 | F19: =F9+F17+F15 -> 29261.38 | G19: =G9+G17+G15 -> 34158.38 | H19: =H9+H17+H15 -> 37788.62 | I19: =I9+I17+I15 -> 40923.42 | J19: =J9+J17+J15 -> 47095.708 | K19: =K9+K17+K15 -> 52303.558 | L19: =L9+L17+L15 -> 57893.45 | ... N19: =N9+N17+N15 -> 70423.32
B24: Two Wheelers (Breakdown)
B26: Total Capacity | E26: 95 | F26: 95 | G26: 95 | H26: 95 | I26: 95 | J26: 95 | K26: 95 | L26: 97 | M26: 99 | N26: 101
B27: Sales Volume (two wheelers) | E27: 58 | F27: 49 | G27: 53 | H27: 56 | I27: 59 | J27: =J29+J31 -> 62.740617 | K27: =K29+K31 -> 66.324248 | L27: =L29+L31 -> 70.065273 | M27: =M29+M31 -> 73.938182 | N27: =N29+N31 -> 77.247434
B28: YOY | E28: - | F28: =(F27-E27)/E27 -> -0.15517241 | G28: =(G27-F27)/F27 -> 0.081632653 | H28: =(H27-G27)/G27 -> 0.056603774 | I28: =(I27-H27)/H27 -> 0.053571429 | J28: =(J27-I27)/I27 -> 0.063400295 | K28: =(K27-J27)/J27 -> 0.057118187 | L28: =(L27-K27)/K27 -> 0.056405086 | M28: =(M27-L27)/L27 -> 0.05527573 | N28: =(N27-M27)/M27 -> 0.04475702
B29: Domestic | E29: 56 | F29: 46.4 | G29: 51.56 | H29: 54.2 | I29: 55.4 | J29: =J54 -> 60.212617 | K29: =K54 -> 63.729048 | L29: =L54 -> 67.368793 | M29: =M54 -> 71.21543 | N29: =N54 -> 74.57755
B30: YOY | E30: - | F30: =(F29-E29)/E29 -> -0.17142857 | G30: =(G29-F29)/F29 -> 0.1112069 | H30: =(H29-G29)/G29 -> 0.051202483 | I30: =(I29-H29)/H29 -> 0.022140221 | J30: =(J29-I29)/I29 -> 0.086870351 | K30: =(K29-J29)/J29 -> 0.058400223 | L30: =(L29-K29)/K29 -> 0.057112808 | M30: =(M29-L29)/L29 -> 0.057098205 | N30: =(N29-M29)/M29 -> 0.047210554
B31: Export | E31: 2 | F31: 2.6 | G31: 1.44 | H31: 1.8 | I31: 3.6 | J31: =40%*I31+30%*H31+20%*G31+10%*F31 -> 2.528 | K31: =40%*J31+30%*I31+20%*H31+10%*G31 -> 2.5952 | L31: =40%*K31+30%*J31+20%*I31+10%*H31 -> 2.69648 | M31: =40%*L31+30%*K31+20%*J31+10%*I31 -> 2.722752 | N31: =40%*M31+30%*L31+20%*K31+10%*J31 -> 2.6698848
B32: YOY | E32: - | F32: =(F31-E31)/E31 -> 0.3 | G32: =(G31-F31)/F31 -> -0.44615385 | H32: =(H31-G31)/G31 -> 0.25 | I32: =(I31-H31)/H31 -> 1 | J32: 0.2 | K32: 0.25 | L32: 0.3 | M32: 0.2 | N32: 0.15
B33: Capacity Utilization % | E33: =E27/E26 -> 0.61052632 | F33: =F27/F26 -> 0.51578947 | G33: =G27/G26 -> 0.55789474 | H33: =H27/H26 -> 0.58947368 | I33: =I27/I26 -> 0.62105263 | J33: =J27/J26 -> 0.66042755 | K33: =K27/K26 -> 0.69814998 | L33: =L27/L26 -> 0.7223224 | ... N33: =N27/N26 -> 0.76482608
B34: Realization (How much rs you get per vehicle sold) | E34: =(E5/AVERAGE(D27:E27)) -> 462.47017 | F34: =(F5/AVERAGE(E27:F27)) -> 453.74617 | G34: =(G5/AVERAGE(F27:G27)) -> 556.8702 | H34: =(H5/AVERAGE(G27:H27)) -> 574.79523 | I34: =(I5/AVERAGE(H27:I27)) -> 589.67965 | J34: =I34*(1+J35) -> 622.70171 | K34: =J34*(1+K35) -> 655.20674 | L34: =K34*(1+L35) -> 684.59276 | M34: =L34*(1+M35) -> 715.45934 | N34: =M34*(1+N35) -> 750.89917
B35: Realization Growth % | E35: - | F35: 0.0712 | G35: 0.0816 | H35: 0.0439 | I35: 0.0273 | J35: =AVERAGE(F35:I35) -> 0.056 | K35: =AVERAGE(G35:J35) -> 0.0522 | L35: =AVERAGE(H35:K35) -> 0.04485 | M35: =AVERAGE(I35:L35) -> 0.0450875 | N35: =AVERAGE(J35:M35) -> 0.049534375
B39: NOTE: Realization Growth % for FY26 is estimated to be 5.6% as according to investor presentation & annual reports, the company is focusing on premium motorcycles scaling, export expansion and EV segment.
B42: Two Wheelers (Domestic Breakdown)
B44: Entry Segment | E44: NA | F44: 11.65 | G44: 10.52 | H44: 10.3 | I44: 9.7 | J44: =I44*(1+J45) -> 9.894 | K44: =J44*(1+K45) -> 10.09188 | L44: =K44*(1+L45) -> 10.243258 | M44: =L44*(1+M45) -> 10.396907 | N44: =M44*(1+N45) -> 10.500876
B45: YOY | F45: - | G45: =(G44-F44)/F44 -> -0.096995708 | H45: =(H44-G44)/G44 -> -0.020912548 | I45: =(I44-H44)/H44 -> -0.058252427 | J45: 0.02 | K45: 0.02 | L45: 0.015 | M45: 0.015 | N45: 0.01
B46: 125 cc deluxe sales | E46: NA | F46: 3.6 | G46: 4.1 | H46: 5.4 | I46: 6.9 | J46: =I46*(1+J47) -> 8.28 | K46: =J46*(1+K47) -> 9.4392 | L46: =K46*(1+L47) -> 10.38312 | M46: =L46*(1+M47) -> 11.109938 | N46: =M46*(1+N47) -> 11.554336
B47: YOY | F47: - | G47: =(G46-F46)/F46 -> 0.13888889 | H47: =(H46-G46)/G46 -> 0.31707317 | I47: =(I46-H46)/H46 -> 0.27777778 | J47: 0.2 | K47: 0.14 | L47: 0.1 | M47: 0.07 | N47: 0.04
B48: Scooter Segment sales | E48: NA | F48: 3.05 | G48: 3.59 | H48: 3.8 | I48: 3.3 | J48: =I48*(1+J49) -> 3.4143627 | K48: =J48*(1+K49) -> 3.5167935 | L48: =K48*(1+L49) -> 3.6222973 | M48: =L48*(1+M49) -> 3.7309663 | N48: =M48*(1+N49) -> 3.8428953
B49: YOY | F49: - | G49: =(G48-F48)/F48 -> 0.17704918 | H49: =(H48-G48)/G48 -> 0.058495822 | I49: =(I48-H48)/H48 -> -0.13157895 | J49: =AVERAGE(G49:I49) -> 0.034655352 | K49: 0.03 | L49: 0.03 | M49: 0.03 | N49: 0.03
B50: 100 cc deluxe segment | E50: NA | F50: 27.45 | G50: 32.65 | H50: 33.6 | I50: 34.8 | J50: =I50*(1+J51) -> 37.749255 | K50: =J50*(1+K51) -> 39.631174 | L50: =K50*(1+L51) -> 41.881117 | M50: =L50*(1+M51) -> 44.552768 | N50: =M50*(1+N51) -> 47.08361
B51: YOY | F51: - | G51: =(G50-F50)/F50 -> 0.18943534 | H51: =(H50-G50)/G50 -> 0.029096478 | I51: =(I50-H50)/H50 -> 0.035714286 | J51: =AVERAGE(G51:I51) -> 0.0847487 | K51: =AVERAGE(H51:J51) -> 0.049853155 | L51: =AVERAGE(I51:K51) -> 0.056772047 | M51: =AVERAGE(J51:L51) -> 0.063791301 | N51: =AVERAGE(K51:M51) -> 0.056805501
B52: Premium segment & EV sales | E52: NA | F52: 0.67 | G52: 0.69 | H52: 0.9 | I52: 0.7 | J52: =I52*(1+J53) -> 0.875 | K52: =J52*(1+K53) -> 1.05 | L52: =K52*(1+L53) -> 1.239 | M52: =L52*(1+M53) -> 1.42485 | N52: =M52*(1+N53) -> 1.595832
B53: YOY | F53: - | G53: =(G52-F52)/F52 -> 0.029850746 | H53: =(H52-G52)/G52 -> 0.30434783 | I53: =(I52-H52)/H52 -> -0.22222222 | J53: 0.25 | K53: 0.2 | L53: 0.18 | M53: 0.15 | N53: 0.12
B54: Total | E54: NA | F54: =F44+F46+F48+F50+F52 -> 46.42 | G54: =G44+G46+G48+G50+G52 -> 51.55 | H54: =H44+H46+H48+H50+H52 -> 54 | I54: =I44+I46+I48+I50+I52 -> 55.4 | J54: =J44+J46+J48+J50+J52 -> 60.212617 | K54: =K44+K46+K48+K50+K52 -> 63.729048 | L54: =L44+L46+L48+L50+L52 -> 67.368793 | M54: =M44+M46+M48+M50+M52 -> 71.21543 | N54: =N44+N46+N48+N50+N52 -> 74.57755
B56: NOTE: Figures for FY21 are not available
B57: NOTE: Segment wise breakdown of exports is NA
B58: NOTE: For forecasting future values, I have made some assumptions based on my understanding of the company after reviewing its annual reports and investor presentations.
B60: Strategy for Future
B61: Grow the core (already high market share)
B62: Capture the EV and premium segment
B63: Invest heavily in EV and premium segment
B64: Partnership with Ather, Harley Davidson & Zero Motorcycles
B65: Hero's plan is to expand globally -->
B66: Brazil operations to start in Q4 FY25
B67: Philippines launched in Aug’24
B68: Expansion into South East Asia
... B79: revenue is a flow metric

Sheet Schedule Populated 
B2: Capex Schedule | C2: Notes | E2: FY21 | F2: FY22 | G2: FY23 | H2: FY24 | I2: FY25 | J2: FY26E | K2: FY27E | L2: FY28E | M2: FY29E | N2: FY30E
B4: Property, Plant & Equipment | E4: ='Balance Sheet '!E5 -> 5550.67 | F4: ='Balance Sheet '!F5 -> 5354.34 | G4: ='Balance Sheet '!G5 -> 5159.42 | H4: ='Balance Sheet '!H5 -> 5212.58 | I4: ='Balance Sheet '!I5 -> 5219.13 | J4: =J11 -> 5622.7723 | K4: =K11 -> 6126.482 | L4: =L11 -> 6664.6926 | M4: =M11 -> 7242.9201 | N4: =N11 -> 7868.2906
B5: Right-of-use Assets | E5: ='Balance Sheet '!E7 -> 511.24 | F5: ='Balance Sheet '!F7 -> 517.9 | G5: ='Balance Sheet '!G7 -> 481.28 | H5: ='Balance Sheet '!H7 -> 475.97 | I5: ='Balance Sheet '!I7 -> 483.39 | J5: =J15 -> 519.4885 | K5: =K15 -> 555.6034 | L5: =L15 -> 583.34714 | M5: =M15 -> 616.0817 | N5: =N15 -> 651.33107
B6: Other Intangible Assets | E6: ='Balance Sheet '!E8 -> 318.48 | F6: ='Balance Sheet '!F8 -> 321.3 | G6: ='Balance Sheet '!G8 -> 518.5 | H6: ='Balance Sheet '!H8 -> 543.65 | I6: ='Balance Sheet '!I8 -> 580.46 | J6: =J19 -> 779.2849 | K6: =K19 -> 848.41352 | L6: =L19 -> 927.63771 | M6: =M19 -> 1019.7033 | N6: =N19 -> 1135.9969
B8: Property, Plant & Equipment
B9: Gross Long Term Assets | E9: 10066.97 | F9: 10347.54 | G9: 10653.19 | H9: 11174.48 | I9: 11699.01 | J9: =I9+J33 -> 12800.754 | K9: =J9+K33 -> 14057.337 | L9: =K9+L33 -> 15412.509 | M9: =L9+M33 -> 16883.04 | N9: =M9+N33 -> 18489.186
B10: Accumulated Depreciation | E10: 4516.3 | F10: 4993.2 | G10: 5493.77 | H10: 5961.9 | I10: 6479.88 | J10: =I10+J22 -> 7177.9817 | K10: =J10+K22 -> 7930.8551 | L10: =K10+L22 -> 8747.8166 | M10: =L10+M22 -> 9640.1198 | N10: =M10+N22 -> 10620.895
B11: Net PPE | E11: =E9-E10 -> 5550.67 | F11: =F9-F10 -> 5354.34 | G11: =G9-G10 -> 5159.42 | H11: =H9-H10 -> 5212.58 | I11: =I9-I10 -> 5219.13 | J11: =J9-J10 -> 5622.7723 | K11: =K9-K10 -> 6126.482 | L11: =L9-L10 -> 6664.6926 | ... N11: =N9-N10 -> 7868.2906
B12: Right-of-use Assets
B13: Gross Long Term Assets | E13: 609.1 | F13: 650.26 | G13: 645.07 | H13: 615.2 | I13: 657.38 | J13: =I13+J39 -> 736.616 | K13: =J13+K39 -> 814.26349 | L13: =K13+L39 -> 889.02216 | M13: =L13+M39 -> 973.64904 | N13: =M13+N39 -> 1067.0552
B14: Accumulated Amortisaton/Depreciation | E14: 97.86 | F14: 132.36 | G14: 163.79 | H14: 139.23 | I14: 173.99 | J14: =I14+J26 -> 217.1275 | K14: =J14+K26 -> 258.66009 | L14: =K14+L26 -> 305.67502 | M14: =L14+M26 -> 357.56733 | N14: =M14+N26 -> 415.72413
B15: Net PPE | E15: =E13-E14 -> 511.24 | F15: =F13-F14 -> 517.9 | G15: =G13-G14 -> 481.28 | H15: =H13-H14 -> 475.97 | I15: =I13-I14 -> 483.39 | J15: =J13-J14 -> 519.4885 | K15: =K13-K14 -> 555.6034 | L15: =L13-L14 -> 583.34714 | ... N15: =N13-N14 -> 651.33107
B16: Other Intangible Assets
B17: Gross Long Term Assets | E17: 4147.94 | F17: 4202.16 | G17: 4468 | H17: 4625.09 | I17: 4830.16 | J17: =I17+J36 -> 5133.442 | K17: =J17+K36 -> 5321.4648 | L17: =K17+L36 -> 5535.4743 | M17: =L17+M36 -> 5778.0878 | N17: =M17+N36 -> 6049.0742
B18: Accumulated Amortisaton/Depreciation | D18: ` | E18: 3829.46 | F18: 3880.86 | G18: 3949.5 | H18: 4081.44 | I18: 4249.7 | J18: =I18+J24 -> 4354.1571 | K18: =J18+K24 -> 4473.0513 | L18: =K18+L24 -> 4607.8366 | M18: =L18+M24 -> 4758.3845 | N18: =M18+N24 -> 4913.0772
B19: Net PPE | E19: =E17-E18 -> 318.48 | F19: =F17-F18 -> 321.3 | G19: =G17-G18 -> 518.5 | H19: =H17-H18 -> 543.65 | I19: =I17-I18 -> 580.46 | J19: =J17-J18 -> 779.2849 | K19: =K17-K18 -> 848.41352 | L19: =L17-L18 -> 927.63771 | ... N19: =N17-N18 -> 1135.9969
B22: Depreciation on PPE | E22: 620.28 | F22: 603.85 | G22: 591.91 | H22: 592.39 | I22: 612.08 | J22: =J23*AVERAGE(I9:J9) -> 698.10172 | K22: =K23*AVERAGE(J9:K9) -> 752.8734 | L22: =L23*AVERAGE(K9:L9) -> 816.9615 | M22: =M23*AVERAGE(L9:M9) -> 892.3032 | N22: =N23*AVERAGE(M9:N9) -> 980.77528
B23: As a % of GLTA | E23: =E22/AVERAGE(D9:E9) -> 0.061615362 | F23: =F22/AVERAGE(E9:F9) -> 0.059158902 | G23: =G22/AVERAGE(F9:G9) -> 0.056370421 | H23: =H22/AVERAGE(G9:H9) -> 0.054278812 | I23: =I22/AVERAGE(H9:I9) -> 0.053518724 | J23: =AVERAGE(E23:I23) -> 0.056988444 | K23: =AVERAGE(F23:J23) -> 0.056063061 | L23: =AVERAGE(G23:K23) -> 0.055443893 | M23: =AVERAGE(H23:L23) -> 0.055258587 | N23: =AVERAGE(I23:M23) -> 0.055454542
B24: Depreciation on Intangible Asset | E24: 50.13 | F24: 51.43 | G24: 68.96 | H24: 131.34 | I24: 168.49 | J24: =J25*AVERAGE(I17:J17) -> 104.4571 | K24: =K25*AVERAGE(J17:K17) -> 118.89416 | L24: =L25*AVERAGE(K17:L17) -> 134.7853 | M24: =M25*AVERAGE(L17:M17) -> 150.54797 | N24: =N25*AVERAGE(M17:N17) -> 154.6927
B25: As a % of GLTA | E25: =E24/AVERAGE(D17:E17) -> 0.012085517 | F25: =F24/AVERAGE(E17:F17) -> 0.012318415 | G25: =G24/AVERAGE(F17:G17) -> 0.015907434 | H25: =H24/AVERAGE(G17:H17) -> 0.02888787 | I25: =I24/AVERAGE(H17:I17) -> 0.03563946 | J25: =AVERAGE(E25:I25) -> 0.020967739 | K25: =AVERAGE(F25:J25) -> 0.022744184 | L25: =AVERAGE(G25:K25) -> 0.024829337 | M25: =AVERAGE(H25:L25) -> 0.026613718 | N25: =AVERAGE(I25:M25) -> 0.026158888
B26: Depreciation on Right of use Assets | E26: 44.71 | F26: 34.24 | G26: 38.29 | H26: 33.63 | I26: 44.02 | J26: =J27*AVERAGE(I13:J13) -> 43.137497 | K26: =K27*AVERAGE(I13:J13) -> 41.532594 | L26: =L27*AVERAGE(J13:K13) -> 47.01493 | M26: =M27*AVERAGE(K13:L13) -> 51.892313 | N26: =N27*AVERAGE(L13:M13) -> 58.156799
B27: As a % of GLTA | E27: =E26/AVERAGE(D13:E13) -> 0.073403382 | F27: =F26/AVERAGE(E13:F13) -> 0.054376826 | G27: =G26/AVERAGE(F13:G13) -> 0.05912007 | H27: =H26/AVERAGE(G13:H13) -> 0.053369516 | I27: =I26/AVERAGE(H13:I13) -> 0.069182291 | J27: =AVERAGE(E27:I27) -> 0.061890417 | K27: =AVERAGE(F27:J27) -> 0.059587824 | L27: =AVERAGE(G27:K27) -> 0.060630024 | M27: =AVERAGE(H27:L27) -> 0.060932014 | N27: =AVERAGE(I27:M27) -> 0.062444514
B28: Total Depreciation | E28: =E22+E24+E26 -> 715.12 | F28: =F22+F24+F26 -> 689.52 | G28: =G22+G24+G26 -> 699.16 | H28: =H22+H24+H26 -> 757.36 | I28: =I22+I24+I26 -> 824.59 | J28: =J22+J24+J26 -> 845.69632 | K28: =K22+K24+K26 -> 913.30015 | L28: =L22+L24+L26 -> 998.76173 | ... N28: =N22+N24+N26 -> 1193.6248
J30: 0.8 | K30: 0.8 | L30: 0.8 | M30: 0.8 | N30: 0.8
B31: Maintenance Capex on PPE | J31: =I22 -> 612.08 | K31: =J22 -> 698.10172 | L31: =K22 -> 752.8734 | M31: =L22 -> 816.9615 | N31: =M22 -> 892.3032
B32: Growth Capex On PPE | J32: =J31*J30 -> 489.664 | K32: =K31*K30 -> 558.48137 | L32: =L31*L30 -> 602.29872 | M32: =M31*M30 -> 653.5692 | N32: =N31*N30 -> 713.84256
B33: Total Capex On PPE | J33: =J31+J32 -> 1101.744 | K33: =K31+K32 -> 1256.5831 | L33: =L31+L32 -> 1355.1721 | M33: =M31+M32 -> 1470.5307 | N33: =N31+N32 -> 1606.1458
B34: Maintenance Capex on Intangible Assets | J34: =I24 -> 168.49 | K34: =J24 -> 104.4571 | L34: =K24 -> 118.89416 | M34: =L24 -> 134.7853 | N34: =M24 -> 150.54797
B35: Growth Capex On Intangible Assets | J35: =J34*J30 -> 134.792 | K35: =K34*K30 -> 83.565683 | L35: =L34*L30 -> 95.115328 | M35: =M34*M30 -> 107.82824 | N35: =N34*N30 -> 120.43838
B36: Total Capex On Intangible Assets | J36: =J34+J35 -> 303.282 | K36: =K34+K35 -> 188.02279 | L36: =L34+L35 -> 214.00949 | M36: =M34+M35 -> 242.61354 | N36: =N34+N35 -> 270.98635
B37: Maintenance Capex on Right of Use of Assets | J37: =I26 -> 44.02 | K37: =J26 -> 43.137497 | L37: =K26 -> 41.532594 | M37: =L26 -> 47.01493 | N37: =M26 -> 51.892313
B38: Growth Capex On Right of Use of Assets | J38: =J37*J30 -> 35.216 | K38: =K37*K30 -> 34.509998 | L38: =L37*L30 -> 33.226075 | M38: =M37*M30 -> 37.611944 | N38: =N37*N30 -> 41.51385
B39: Total Capex On Right of use of Assets | J39: =J37+J38 -> 79.236 | K39: =K37+K38 -> 77.647494 | L39: =L37+L38 -> 74.75867 | M39: =M37+M38 -> 84.626874 | N39: =N37+N38 -> 93.406164
B40: Total Capex | J40: =J33+J36+J39 -> 1484.262 | K40: =K33+K36+K39 -> 1522.2534 | L40: =L33+L36+L39 -> 1643.9403 | M40: =M33+M36+M39 -> 1797.7711 | N40: =N33+N36+N39 -> 1970.5383
B44: NOTE: Used problem of selection. Since all the numbers are in a narrow range, I have taken the avg of all 5
B49: Debt Schedule | C49: Notes | E49: FY21 | F49: FY22 | G49: FY23 | H49: FY24 | I49: FY25 | J49: FY26E | K49: FY27E | L49: FY28E | M49: FY29E | N49: FY30E
B51: Long term Borrowings (ncl) | E51: ='Balance Sheet '!E41 -> 45.18 | F51: ='Balance Sheet '!F41 -> 36.17 | G51: ='Balance Sheet '!G41 -> 20.09 | H51: 0 | I51: 0 | J51: =I51+J68 -> 1.0045 | K51: =J51+K68 -> 1.0045 | L51: =K51+L68 -> 1.0045 | M51: =L51+M68 -> 1.054725 | N51: =M51+N68 -> 1.10495
B52: Short Term Borrowing (cl) | C52: From WC Schedule | E52: ='Balance Sheet '!E49 -> 296.85 | F52: ='Balance Sheet '!F49 -> 317.31 | G52: ='Balance Sheet '!G49 -> 293.15 | H52: ='Balance Sheet '!H49 -> 363.43 | I52: ='Balance Sheet '!I49 -> 456.76 | J52: =J93 -> 482.78834 | K52: =K93 -> 541.51122 | L52: =L93 -> 587.77754 | M52: =M93 -> 657.2064 | N52: =N93 -> 727.50327
B53: Total Borrowings | E53: =SUM(E51:E52) -> 342.03 | F53: =SUM(F51:F52) -> 353.48 | G53: =SUM(G51:G52) -> 313.24 | H53: =SUM(H51:H52) -> 363.43 | I53: =SUM(I51:I52) -> 456.76 | J53: =SUM(J51:J52) -> 483.79284 | K53: =SUM(K51:K52) -> 542.51572 | L53: =SUM(L51:L52) -> 588.78204 | ... N53: =SUM(N51:N52) -> 728.60822
B55: Long Term Lease (ncl) | E55: ='Balance Sheet '!E42 -> 212.42 | F55: ='Balance Sheet '!F42 -> 215.51 | G55: ='Balance Sheet '!G42 -> 219.67 | H55: ='Balance Sheet '!H42 -> 199.13 | I55: ='Balance Sheet '!I42 -> 196.21 | J55: =I55+J73 -> 206.0205 | K55: =J55+K73 -> 216.32153 | L55: =K55+L73 -> 227.1376 | M55: =L55+M73 -> 238.49448 | N55: =M55+N73 -> 250.41921
B56: Short Term Lease (cl) | C56: From WC Schedule | E56: ='Balance Sheet '!E50 -> 29.57 | F56: ='Balance Sheet '!F50 -> 36.18 | G56: ='Balance Sheet '!G50 -> 34.63 | H56: ='Balance Sheet '!H50 -> 43.85 | I56: ='Balance Sheet '!I50 -> 46.96 | J56: =J94 -> 53.108044 | K56: =K94 -> 59.436858 | L56: =L94 -> 65.131493 | M56: =M94 -> 72.598194 | N56: =N94 -> 79.751247
B57: Total Lease | E57: =SUM(E55:E56) -> 241.99 | F57: =SUM(F55:F56) -> 251.69 | G57: =SUM(G55:G56) -> 254.3 | H57: =SUM(H55:H56) -> 242.98 | I57: =SUM(I55:I56) -> 243.17 | J57: =SUM(J55:J56) -> 259.12854 | K57: =SUM(K55:K56) -> 275.75838 | L57: =SUM(L55:L56) -> 292.26909 | ... N57: =SUM(N55:N56) -> 330.17045
B59: Cost on Borrowings | E59: 22.63 | F59: 25.05 | G59: 82.72 | H59: 55.08 | I59: 47.97 | J59: =J63*AVERAGE(I53:J53) -> 62.650933 | K59: =K63*AVERAGE(J53:K53) -> 75.245378 | L59: =L63*AVERAGE(K53:L53) -> 91.382255 | M59: =M63*AVERAGE(L53:M53) -> 89.933966 | N59: =N63*AVERAGE(M53:N53) -> 97.443652
B60: Cost on Lease Liabilities | E60: 19.12 | F60: 23.68 | G60: 18.02 | H60: 16.31 | I60: 17.61 | J60: =J64*AVERAGE(I57:J57) -> 19.299036 | K60: =K64*AVERAGE(J57:K57) -> 20.435131 | L60: =L64*AVERAGE(K57:L57) -> 20.592267 | M60: =M64*AVERAGE(L57:M57) -> 21.95031 | N60: =N64*AVERAGE(M57:N57) -> 23.788511
B61: Total Finance cost | E61: =SUM( E59:E60) -> 41.75 | F61: =SUM( F59:F60) -> 48.73 | G61: =SUM( G59:G60) -> 100.74 | H61: =SUM( H59:H60) -> 71.39 | I61: =SUM( I59:I60) -> 65.58 | J61: =SUM( J59:J60) -> 81.949969 | K61: =SUM( K59:K60) -> 95.680508 | L61: =SUM( L59:L60) -> 111.97452 | ... N61: =SUM( N59:N60) -> 121.23216
B63: Cost of Borrowing (%) | E63: =E59/AVERAGE(D53:E53) -> 0.066163787 | F63: =F59/AVERAGE(E53:F53) -> 0.072033472 | G63: =G59/AVERAGE(F53:G53) -> 0.24814015 | H63: =H59/AVERAGE(G53:H53) -> 0.16279723 | I63: =I59/AVERAGE(H53:I53) -> 0.1169729 | J63: =AVERAGE(E63:I63) -> 0.13322151 | K63: =AVERAGE(F63:J63) -> 0.14663305 | L63: =AVERAGE(G63:K63) -> 0.16155297 | M63: =AVERAGE(H63:L63) -> 0.14423553 | N63: =AVERAGE(I63:M63) -> 0.14052319
B64: Cost Of Lease (%) | E64: =E60/AVERAGE(D57:E57) -> 0.079011529 | F64: =F60/AVERAGE(E57:F57) -> 0.095932588 | G64: =G60/AVERAGE(F57:G57) -> 0.071226704 | H64: =H60/AVERAGE(G57:H57) -> 0.065596847 | I64: =I60/AVERAGE(H57:I57) -> 0.072446776 | J64: =AVERAGE(E64:I64) -> 0.076842889 | K64: =AVERAGE(F64:J64) -> 0.076409161 | L64: =AVERAGE(G64:K64) -> 0.072504475 | M64: =AVERAGE(H64:L64) -> 0.072760029 | N64: =AVERAGE(I64:M64) -> 0.074192666
B65: Weighted Average Cost Of Borrowing | J65: =J61/(AVERAGE(I57:J57)+AVERAGE(I53:J53)) -> 0.11359447
B66: New Borrowing Raised | I66: 0.1 | J66: =G51*10% -> 2.009 | K66: =H51*10% -> 0 | L66: =I51*10% -> 0 | M66: =J51*10% -> 0.10045 | N66: =K51*10% -> 0.10045
B67: Exsisting Borrowing Repaid | I67: 0.05 | J67: =G51*5% -> 1.0045 | K67: =H51*5% -> 0 | L67: =I51*5% -> 0 | M67: =J51*5% -> 0.050225 | N67: =K51*5% -> 0.050225
B68: Net Borrowing Raised | I68: =I66-I67 -> 0.05 | J68: =J66-J67 -> 1.0045 | K68: =K66-K67 -> 0 | L68: =L66-L67 -> 0 | M68: =M66-M67 -> 0.050225 | N68: =N66-N67 -> 0.050225
B69: Net Borrowing Added to Long Term Borrowings
B71: New Lease added | I71: 0.1 | J71: =I55*10% -> 19.621 | K71: =J55*10% -> 20.60205 | L71: =K55*10% -> 21.632153 | M71: =L55*10% -> 22.71376 | N71: =M55*10% -> 23.849448
B72: Existing lease removed | I72: 0.05 | J72: =I55*5% -> 9.8105 | K72: =J55*5% -> 10.301025 | L72: =K55*5% -> 10.816076 | M72: =L55*5% -> 11.35688 | N72: =M55*5% -> 11.924724
B73: Net Lease added | I73: =I71-I72 -> 0.05 | J73: =J71-J72 -> 9.8105 | K73: =K71-K72 -> 10.301025 | L73: =L71-L72 -> 10.816076 | M73: =M71-M72 -> 11.35688 | N73: =N71-N72 -> 11.924724
B74: Net Lease added to long term lease
B78: Working Capital Schedule | C78: Notes | E78: FY21 | F78: FY22 | G78: FY23 | H78: FY24 | I78: FY25 | J78: FY26E | K78: FY27E | L78: FY28E | M78: FY29E | N78: FY30E
B81: Current Assets (except cash & equivalents)
B82: Inventories | E82: ='Balance Sheet '!E20 -> 1789.27 | F82: ='Balance Sheet '!F20 -> 1472.41 | G82: ='Balance Sheet '!G20 -> 1756.39 | H82: ='Balance Sheet '!H20 -> 1755.9 | I82: ='Balance Sheet '!I20 -> 2013.34 | J82: =J106*'Revenue Model'!J$19/365 -> 2334.6416 | K82: =K106*'Revenue Model'!K$19/365 -> 2584.2506 | L82: =L106*'Revenue Model'!L$19/365 -> 2856.664 | M82: =M106*'Revenue Model'!M$19/365 -> 3140.9796 | N82: =N106*'Revenue Model'!N$19/365 -> 3468.6563
B83: Financial Assets
B84: i) Investments | E84: ='Balance Sheet '!E22 -> 6225.34 | F84: ='Balance Sheet '!F22 -> 5870.31 | G84: ='Balance Sheet '!G22 -> 3671.85 | H84: ='Balance Sheet '!H22 -> 4305.08 | I84: ='Balance Sheet '!I22 -> 6635.99 | J84: =J108*'Revenue Model'!J$19/365 -> 7062.4459 | K84: =K108*'Revenue Model'!K$19/365 -> 7889.1709 | L84: =L108*'Revenue Model'!L$19/365 -> 8318.0845 | M84: =M108*'Revenue Model'!M$19/365 -> 9299.7638 | N84: =N108*'Revenue Model'!N$19/365 -> 10389.496
B85: ii) Trade Receivables | E85: ='Balance Sheet '!E23 -> 2274.68 | F85: ='Balance Sheet '!F23 -> 2158.49 | G85: ='Balance Sheet '!G23 -> 2719.47 | H85: ='Balance Sheet '!H23 -> 2630.22 | I85: ='Balance Sheet '!I23 -> 3381.29 | J85: =J109*'Revenue Model'!J$19/365 -> 3608.2971 | K85: =K109*'Revenue Model'!K$19/365 -> 4065.6725 | L85: =L109*'Revenue Model'!L$19/365 -> 4472.9614 | M85: =M109*'Revenue Model'!M$19/365 -> 4934.3841 | N85: =N109*'Revenue Model'!N$19/365 -> 5473.2641
B86: v) Loans | E86: ='Balance Sheet '!E26 -> 22.95 | F86: ='Balance Sheet '!F26 -> 22.81 | G86: ='Balance Sheet '!G26 -> 23.71 | H86: ='Balance Sheet '!H26 -> 24.56 | I86: ='Balance Sheet '!I26 -> 27.07 | J86: =J110*'Revenue Model'!J$19/365 -> 32.075261 | K86: =K110*'Revenue Model'!K$19/365 -> 35.735237 | L86: =L110*'Revenue Model'!L$19/365 -> 39.261237 | M86: =M110*'Revenue Model'!M$19/365 -> 43.225673 | N86: =N110*'Revenue Model'!N$19/365 -> 47.621582
B87: vi) Others | E87: ='Balance Sheet '!E27 -> 382.55 | F87: ='Balance Sheet '!F27 -> 475 | G87: ='Balance Sheet '!G27 -> 571.65 | H87: ='Balance Sheet '!H27 -> 423.53 | I87: ='Balance Sheet '!I27 -> 141.59 | J87: =J111*'Revenue Model'!J$19/365 -> 436.99162 | K87: =K111*'Revenue Model'!K$19/365 -> 479.47183 | L87: =L111*'Revenue Model'!L$19/365 -> 555.24343 | M87: =M111*'Revenue Model'!M$19/365 -> 574.7219 | N87: =N111*'Revenue Model'!N$19/365 -> 609.8836
B88: Income tax assets (net) | E88: ='Balance Sheet '!E28 -> 0 | F88: ='Balance Sheet '!F28 -> 0 | G88: 0 | H88: 0 | I88: ='Balance Sheet '!I28 -> 198.12 | J88: =J112*'Revenue Model'!J$19/365 -> 91.200606 | K88: =K112*'Revenue Model'!K$19/365 -> 116.47842 | L88: =L112*'Revenue Model'!L$19/365 -> 113.23148 | M88: =M112*'Revenue Model'!M$19/365 -> 136.18913 | N88: =N112*'Revenue Model'!N$19/365 -> 164.68574
B89: Other current assets | E89: ='Balance Sheet '!E29 -> 279.45 | F89: ='Balance Sheet '!F29 -> 273.46 | G89: ='Balance Sheet '!G29 -> 269.46 | H89: ='Balance Sheet '!H29 -> 479.69 | I89: ='Balance Sheet '!I29 -> 462.41 | J89: =J113*'Revenue Model'!J$19/365 -> 515.88668 | K89: =K113*'Revenue Model'!K$19/365 -> 563.00712 | L89: =L113*'Revenue Model'!L$19/365 -> 624.09651 | M89: =M113*'Revenue Model'!M$19/365 -> 706.22302 | N89: =N113*'Revenue Model'!N$19/365 -> 771.14997
B90: Total Current Assets (except cash & equivalents) | E90: =SUM(E82:E89) -> 10974.24 | F90: =SUM(F82:F89) -> 10272.48 | G90: =SUM(G82:G89) -> 9012.53 | H90: =SUM(H82:H89) -> 9618.98 | I90: =SUM(I82:I89) -> 12859.81 | J90: =SUM(J82:J89) -> 14081.539 | K90: =SUM(K82:K89) -> 15733.787 | L90: =SUM(L82:L89) -> 16979.542 | ... N90: =SUM(N82:N89) -> 20924.757
B91: Current Liabilities
B92: Financial Liabilities
B93: i) Borrowings | E93: ='Balance Sheet '!E49 -> 296.85 | F93: ='Balance Sheet '!F49 -> 317.31 | G93: ='Balance Sheet '!G49 -> 293.15 | H93: ='Balance Sheet '!H49 -> 363.43 | I93: ='Balance Sheet '!I49 -> 456.76 | J93: =J116*'Revenue Model'!J$19/365 -> 482.78834 | K93: =K116*'Revenue Model'!K$19/365 -> 541.51122 | L93: =L116*'Revenue Model'!L$19/365 -> 587.77754 | M93: =M116*'Revenue Model'!M$19/365 -> 657.2064 | N93: =N116*'Revenue Model'!N$19/365 -> 727.50327
B94: ii) Lease Liabilities | E94: ='Balance Sheet '!E50 -> 29.57 | F94: ='Balance Sheet '!F50 -> 36.18 | G94: ='Balance Sheet '!G50 -> 34.63 | H94: ='Balance Sheet '!H50 -> 43.85 | I94: ='Balance Sheet '!I50 -> 46.96 | J94: =J117*'Revenue Model'!J$19/365 -> 53.108044 | K94: =K117*'Revenue Model'!K$19/365 -> 59.436858 | L94: =L117*'Revenue Model'!L$19/365 -> 65.131493 | M94: =M117*'Revenue Model'!M$19/365 -> 72.598194 | N94: =N117*'Revenue Model'!N$19/365 -> 79.751247
B95: iii) Trade Payables – MSME | E95: ='Balance Sheet '!E51 -> 16.68 | F95: ='Balance Sheet '!F51 -> 26.19 | G95: ='Balance Sheet '!G51 -> 2.44 | H95: ='Balance Sheet '!H51 -> 18.74 | I95: ='Balance Sheet '!I51 -> 21.5 | J95: =J118*'Revenue Model'!J$19/365 -> 23.992804 | K95: =K118*'Revenue Model'!K$19/365 -> 26.550806 | L95: =L118*'Revenue Model'!L$19/365 -> 26.929599 | M95: =M118*'Revenue Model'!M$19/365 -> 31.447494 | N95: =N118*'Revenue Model'!N$19/365 -> 34.532949
B96: iv) Trade Payables – Others | E96: ='Balance Sheet '!E52 -> 5247.5 | F96: ='Balance Sheet '!F52 -> 4316.9 | G96: ='Balance Sheet '!G52 -> 4757.7 | H96: ='Balance Sheet '!H52 -> 5604.16 | I96: ='Balance Sheet '!I52 -> 5678.16 | J96: =J119*'Revenue Model'!J$19/365 -> 6858.1797 | K96: =K119*'Revenue Model'!K$19/365 -> 7499.5803 | L96: =L119*'Revenue Model'!L$19/365 -> 8317.8208 | M96: =M119*'Revenue Model'!M$19/365 -> 9199.1083 | N96: =N119*'Revenue Model'!N$19/365 -> 10097.262
B97: v) Other Financial Liabilities | E97: ='Balance Sheet '!E52 -> 5247.5 | F97: ='Balance Sheet '!F52 -> 4316.9 | G97: ='Balance Sheet '!G52 -> 4757.7 | H97: ='Balance Sheet '!H52 -> 5604.16 | I97: ='Balance Sheet '!I53 -> 282.94 | J97: =J120*'Revenue Model'!J$19/365 -> 4374.5974 | K97: =K120*'Revenue Model'!K$19/365 -> 4327.6306 | L97: =L120*'Revenue Model'!L$19/365 -> 5234.2919 | M97: =M120*'Revenue Model'!M$19/365 -> 5490.3948 | N97: =N120*'Revenue Model'!N$19/365 -> 5612.5266
B98: Other Current Liabilities | E98: ='Balance Sheet '!E53 -> 167.52 | F98: ='Balance Sheet '!F53 -> 145.58 | G98: ='Balance Sheet '!G53 -> 169.93 | H98: ='Balance Sheet '!H53 -> 254.9 | I98: ='Balance Sheet '!I54 -> 768.17 | J98: =J121*'Revenue Model'!J$19/365 -> 521.2592 | K98: =K121*'Revenue Model'!K$19/365 -> 613.4183 | L98: =L121*'Revenue Model'!L$19/365 -> 640.34505 | M98: =M121*'Revenue Model'!M$19/365 -> 742.38567 | N98: =N121*'Revenue Model'!N$19/365 -> 853.20606
B99: Provisions | E99: ='Balance Sheet '!E54 -> 570.59 | F99: ='Balance Sheet '!F54 -> 496.32 | G99: ='Balance Sheet '!G54 -> 562.09 | H99: ='Balance Sheet '!H54 -> 603.85 | I99: ='Balance Sheet '!I55 -> 221.49 | J99: =J122*'Revenue Model'!J$19/365 -> 571.90982 | K99: =K122*'Revenue Model'!K$19/365 -> 597.34777 | L99: =L122*'Revenue Model'!L$19/365 -> 694.49695 | M99: =M122*'Revenue Model'!M$19/365 -> 740.91933 | N99: =N122*'Revenue Model'!N$19/365 -> 783.65653
B100: Total Current Liabilities | E100: =SUM(E93:E99) -> 11576.21 | F100: =SUM(F93:F99) -> 9655.38 | G100: =SUM(G93:G99) -> 10577.64 | H100: =SUM(H93:H99) -> 12493.09 | I100: =SUM(I93:I99) -> 7475.98 | J100: =SUM(J93:J99) -> 12885.835 | K100: =SUM(K93:K99) -> 13665.476 | L100: =SUM(L93:L99) -> 15566.793 | ... N100: =SUM(N93:N99) -> 18188.439
B101: Net Working Capital (excluding cash) | E101: =E90-E100 -> -601.97 | F101: =F90-F100 -> 617.1 | G101: =G90-G100 -> -1565.11 | H101: =H90-H100 -> -2874.11 | I101: =I90-I100 -> 5383.83 | J101: =J90-J100 -> 1195.7035 | K101: =K90-K100 -> 2068.3108 | L101: =L90-L100 -> 1412.7491 | ... N101: =N90-N100 -> 2736.3181
B102: Change in Net Working Capital | E102: =E101-D101 -> -601.97 | F102: =F101-E101 -> 1219.07 | G102: =G101-F101 -> -2182.21 | H102: =H101-G101 -> -1309 | I102: =I101-H101 -> 8257.94 | J102: =J101-I101 -> -4188.1265 | K102: =K101-J101 -> 872.60736 | L102: =L101-K101 -> -655.56167 | ... N102: =N101-M101 -> 834.8911
B105: Current Assets as days of sales | C105: Notes | E105: FY21 | F105: FY22 | G105: FY23 | H105: FY24 | I105: FY25 | J105: FY26E | K105: FY27E | L105: FY28E | M105: FY29E | N105: FY30E
B106: Inventories | E106: =E82*365/'Revenue Model'!E$19 -> 21.094982 | F106: =F82*365/'Revenue Model'!F$19 -> 18.366518 | G106: =G82*365/'Revenue Model'!G$19 -> 18.767938 | H106: =H82*365/'Revenue Model'!H$19 -> 16.960225 | I106: =I82*365/'Revenue Model'!I$19 -> 17.957177 | J106: =I106*40%+H106*30%+G106*10%+F106*10%+E106*10% -> 18.093882 | K106: =J106*40%+I106*30%+H106*10%+G106*10%+F106*10% -> 18.034174 | L106: =K106*40%+J106*30%+I106*10%+H106*10%+G106*10% -> 18.010368 | M106: =L106*40%+K106*30%+J106*10%+I106*10%+H106*10% -> 17.915528 | N106: =M106*40%+L106*30%+K106*10%+J106*10%+I106*10% -> 17.977845
B107: Financial Assets
B108: i) Investments | E108: =E84*365/'Revenue Model'!E$19 -> 73.394979 | F108: =F84*365/'Revenue Model'!F$19 -> 73.224952 | G108: =G84*365/'Revenue Model'!G$19 -> 39.235621 | H108: =H84*365/'Revenue Model'!H$19 -> 41.582736 | I108: =I84*365/'Revenue Model'!I$19 -> 59.187046 | J108: =I108*40%+H108*30%+G108*10%+F108*10%+E108*10% -> 54.735194 | K108: =J108*40%+I108*30%+H108*10%+G108*10%+F108*10% -> 55.054523 | L108: =K108*40%+J108*30%+I108*10%+H108*10%+G108*10% -> 52.442908 | M108: =L108*40%+K108*30%+J108*10%+I108*10%+H108*10% -> 53.044017 | N108: =M108*40%+L108*30%+K108*10%+J108*10%+I108*10% -> 53.848156
B109: ii) Trade Receivables | E109: =E85*365/'Revenue Model'!E$19 -> 26.817827 | F109: =F85*365/'Revenue Model'!F$19 -> 26.924528 | G109: =G85*365/'Revenue Model'!G$19 -> 29.058947 | H109: =H85*365/'Revenue Model'!H$19 -> 25.405275 | I109: =I85*365/'Revenue Model'!I$19 -> 30.158057 | J109: =I109*40%+H109*30%+G109*10%+F109*10%+E109*10% -> 27.964936 | K109: =J109*40%+I109*30%+H109*10%+G109*10%+F109*10% -> 28.372267 | L109: =K109*40%+J109*30%+I109*10%+H109*10%+G109*10% -> 28.200615 | M109: =L109*40%+K109*30%+J109*10%+I109*10%+H109*10% -> 28.144753 | N109: =M109*40%+L109*30%+K109*10%+J109*10%+I109*10% -> 28.367612
B110: v) Loans | E110: =E86*365/'Revenue Model'!E$19 -> 0.27057394 | F110: =F86*365/'Revenue Model'!F$19 -> 0.28452691 | G110: =G86*365/'Revenue Model'!G$19 -> 0.25335364 | H110: =H86*365/'Revenue Model'!H$19 -> 0.23722486 | I110: =I86*365/'Revenue Model'!I$19 -> 0.24143999 | J110: =I110*40%+H110*30%+G110*10%+F110*10%+E110*10% -> 0.2485889 | K110: =J110*40%+I110*30%+H110*10%+G110*10%+F110*10% -> 0.2493781 | L110: =K110*40%+J110*30%+I110*10%+H110*10%+G110*10% -> 0.24752976 | M110: =L110*40%+K110*30%+J110*10%+I110*10%+H110*10% -> 0.24655071 | N110: =M110*40%+L110*30%+K110*10%+J110*10%+I110*10% -> 0.24681991
B111: vi) Others | E111: =E87*365/'Revenue Model'!E$19 -> 4.5101551 | F111: =F87*365/'Revenue Model'!F$19 -> 5.9250452 | G111: =G87*365/'Revenue Model'!G$19 -> 6.1083766 | H111: =H87*365/'Revenue Model'!H$19 -> 4.0908731 | I111: =I87*365/'Revenue Model'!I$19 -> 1.2628551 | J111: =I111*40%+H111*30%+G111*10%+F111*10%+E111*10% -> 3.3867617 | K111: =J111*40%+I111*30%+H111*10%+G111*10%+F111*10% -> 3.3459907 | L111: =K111*40%+J111*30%+I111*10%+H111*10%+G111*10% -> 3.5006353 | M111: =L111*40%+K111*30%+J111*10%+I111*10%+H111*10% -> 3.2781003 | N111: =M111*40%+L111*30%+K111*10%+J111*10%+I111*10% -> 3.1609915
B112: Income tax assets (net) | E112: =E88*365/'Revenue Model'!E$19 -> 0 | F112: =F88*365/'Revenue Model'!F$19 -> 0 | G112: =G88*365/'Revenue Model'!G$19 -> 0 | H112: =H88*365/'Revenue Model'!H$19 -> 0 | I112: =I88*365/'Revenue Model'!I$19 -> 1.7670517 | J112: =I112*40%+H112*30%+G112*10%+F112*10%+E112*10% -> 0.70682069 | K112: =J112*40%+I112*30%+H112*10%+G112*10%+F112*10% -> 0.81284379 | L112: =K112*40%+J112*30%+I112*10%+H112*10%+G112*10% -> 0.7138889 | M112: =L112*40%+K112*30%+J112*10%+I112*10%+H112*10% -> 0.77679594 | N112: =M112*40%+L112*30%+K112*10%+J112*10%+I112*10% -> 0.85355667
B113: Other current assets | E113: =E89*365/'Revenue Model'!E$19 -> 3.2946356 | F113: =F89*365/'Revenue Model'!F$19 -> 3.4110797 | G113: =G89*365/'Revenue Model'!G$19 -> 2.8793198 | H113: =H89*365/'Revenue Model'!H$19 -> 4.6333221 | I113: =I89*365/'Revenue Model'!I$19 -> 4.1242802 | J113: =I113*40%+H113*30%+G113*10%+F113*10%+E113*10% -> 3.9982122 | K113: =J113*40%+I113*30%+H113*10%+G113*10%+F113*10% -> 3.9289411 | L113: =K113*40%+J113*30%+I113*10%+H113*10%+G113*10% -> 3.9347323 | M113: =L113*40%+K113*30%+J113*10%+I113*10%+H113*10% -> 4.0281567 | N113: =M113*40%+L113*30%+K113*10%+J113*10%+I113*10% -> 3.9968257
B114: Current Liabilties as days of sales | C114: Notes | E114: FY21 | F114: FY22 | G114: FY23 | H114: FY24 | I114: FY25 | J114: FY26E | K114: FY27E | L114: FY28E | M114: FY29E | N114: FY30E
B115: Financial Liabilities
B116: i) Borrowings | E116: =E93*365/'Revenue Model'!E$19 -> 3.4997766 | F116: =F93*365/'Revenue Model'!F$19 -> 3.958055 | G116: =G93*365/'Revenue Model'!G$19 -> 3.1324597 | H116: =H93*365/'Revenue Model'!H$19 -> 3.5103677 | I116: =I93*365/'Revenue Model'!I$19 -> 4.0738873 | J116: =I116*40%+H116*30%+G116*10%+F116*10%+E116*10% -> 3.7416943 | K116: =J116*40%+I116*30%+H116*10%+G116*10%+F116*10% -> 3.7789322 | L116: =K116*40%+J116*30%+I116*10%+H116*10%+G116*10% -> 3.7057526 | M116: =L116*40%+K116*30%+J116*10%+I116*10%+H116*10% -> 3.7485756 | N116: =M116*40%+L116*30%+K116*10%+J116*10%+I116*10% -> 3.7706074
B117: ii) Lease Liabilities | E117: =E94*365/'Revenue Model'!E$19 -> 0.34862185 | F117: =F94*365/'Revenue Model'!F$19 -> 0.45130134 | G117: =G94*365/'Revenue Model'!G$19 -> 0.3700395 | H117: =H94*365/'Revenue Model'!H$19 -> 0.42354682 | I117: =I94*365/'Revenue Model'!I$19 -> 0.41884085 | J117: =I117*40%+H117*30%+G117*10%+F117*10%+E117*10% -> 0.41159666 | K117: =J117*40%+I117*30%+H117*10%+G117*10%+F117*10% -> 0.41477968 | L117: =K117*40%+J117*30%+I117*10%+H117*10%+G117*10% -> 0.41063359 | M117: =L117*40%+K117*30%+J117*10%+I117*10%+H117*10% -> 0.41408577 | N117: =M117*40%+L117*30%+K117*10%+J117*10%+I117*10% -> 0.4133461
B118: iii) Trade Payables – MSME | E118: =E95*365/'Revenue Model'!E$19 -> 0.19665243 | F118: =F95*365/'Revenue Model'!F$19 -> 0.32668828 | G118: =G95*365/'Revenue Model'!G$19 -> 0.026072665 | H118: =H95*365/'Revenue Model'!H$19 -> 0.18100952 | I118: =I95*365/'Revenue Model'!I$19 -> 0.19176061 | J118: =I118*40%+H118*30%+G118*10%+F118*10%+E118*10% -> 0.18594844 | K118: =J118*40%+I118*30%+H118*10%+G118*10%+F118*10% -> 0.18528461 | L118: =K118*40%+J118*30%+I118*10%+H118*10%+G118*10% -> 0.16978265 | M118: =L118*40%+K118*30%+J118*10%+I118*10%+H118*10% -> 0.1793703 | N118: =M118*40%+L118*30%+K118*10%+J118*10%+I118*10% -> 0.17898228
B119: iv) Trade Payables – Others | E119: =E96*365/'Revenue Model'!E$19 -> 61.866525 | F119: =F96*365/'Revenue Model'!F$19 -> 53.848058 | G119: =G96*365/'Revenue Model'!G$19 -> 50.838491 | H119: =H96*365/'Revenue Model'!H$19 -> 54.13054 | I119: =I96*365/'Revenue Model'!I$19 -> 50.644066 | J119: =I119*40%+H119*30%+G119*10%+F119*10%+E119*10% -> 53.152096 | K119: =J119*40%+I119*30%+H119*10%+G119*10%+F119*10% -> 52.335767 | L119: =K119*40%+J119*30%+I119*10%+H119*10%+G119*10% -> 52.441245 | M119: =L119*40%+K119*30%+J119*10%+I119*10%+H119*10% -> 52.469899 | N119: =M119*40%+L119*30%+K119*10%+J119*10%+I119*10% -> 52.333526
B120: v) Other Financial Liabilities | E120: =E97*365/'Revenue Model'!E$19 -> 61.866525 | F120: =F97*365/'Revenue Model'!F$19 -> 53.848058 | G120: =G97*365/'Revenue Model'!G$19 -> 50.838491 | H120: =H97*365/'Revenue Model'!H$19 -> 54.13054 | I120: =I97*365/'Revenue Model'!I$19 -> 2.5235696 | J120: =I120*40%+H120*30%+G120*10%+F120*10%+E120*10% -> 33.903897 | K120: =J120*40%+I120*30%+H120*10%+G120*10%+F120*10% -> 30.200339 | L120: =K120*40%+J120*30%+I120*10%+H120*10%+G120*10% -> 33.000565 | M120: =L120*40%+K120*30%+J120*10%+I120*10%+H120*10% -> 31.316128 | N120: =M120*40%+L120*30%+K120*10%+J120*10%+I120*10% -> 29.089401
B121: Other Current Liabilities | E121: =E98*365/'Revenue Model'!E$19 -> 1.9750129 | F121: =F98*365/'Revenue Model'!F$19 -> 1.8159328 | G121: =G98*365/'Revenue Model'!G$19 -> 1.8157902 | H121: =H98*365/'Revenue Model'!H$19 -> 2.4620772 | I121: =I98*365/'Revenue Model'!I$19 -> 6.8513836 | J121: =I121*40%+H121*30%+G121*10%+F121*10%+E121*10% -> 4.0398502 | K121: =J121*40%+I121*30%+H121*10%+G121*10%+F121*10% -> 4.2807352 | L121: =K121*40%+J121*30%+I121*10%+H121*10%+G121*10% -> 4.0371742 | M121: =L121*40%+K121*30%+J121*10%+I121*10%+H121*10% -> 4.2344214 | N121: =M121*40%+L121*30%+K121*10%+J121*10%+I121*10% -> 4.4221177
B122: Provisions | E122: =E99*365/'Revenue Model'!E$19 -> 6.727093 | F122: =F99*365/'Revenue Model'!F$19 -> 6.1909862 | G122: =G99*365/'Revenue Model'!G$19 -> 6.0062231 | H122: =H99*365/'Revenue Model'!H$19 -> 5.8325827 | I122: =I99*365/'Revenue Model'!I$19 -> 1.9754911 | J122: =I122*40%+H122*30%+G122*10%+F122*10%+E122*10% -> 4.4324014 | K122: =J122*40%+I122*30%+H122*10%+G122*10%+F122*10% -> 4.1685871 | L122: =K122*40%+J122*30%+I122*10%+H122*10%+G122*10% -> 4.3785849 | M122: =L122*40%+K122*30%+J122*10%+I122*10%+H122*10% -> 4.2260576 | N122: =M122*40%+L122*30%+K122*10%+J122*10%+I122*10% -> 4.0616465

Sheet WACC
A2: Date | B2: Hero MotoCorp | C2: Date | D2: Nifty 50 | E2: Returns/Hero | F2: Returns/Nifty | K2: CMP | L2: 5472.5
B3: 1639.65 | D3: 8253.8 | E3: =B3/B4-1 -> 0.036408457 | F3: =D3/D4-1 -> 0.021029714 | K3: No of Shares | L3: 20.02
B4: 1582.05 | D4: 8083.8 | E4: =B4/B5-1 -> -0.10578227 | F4: =D4/D5-1 -> -0.080571416
B5: 1769.2 | D5: 8792.2 | E5: =B5/B6-1 -> -0.028792578 | F5: =D5/D6-1 -> 0.0049664238 | I5: Slope | J5: =SLOPE(E3:E1234,F3:F1234) -> 0.86700672
B6: 1821.65 | D6: 8748.75 | E6: =B6/B7-1 -> -0.085011804 | F6: =D6/D7-1 -> -0.039854476 | I6: WACC
B7: 1990.9 | D7: 9111.9 | E7: =B7/B8-1 -> 0.0374404 | F7: =D7/D8-1 -> 0.013125636 | I7: Beta | J7: =_xlfn.COVARIANCE.S(E3:E1234,F3:F1234)/_xlfn.VAR.S(F3:F1234) -> 0.86700672 | K7: =+cov(rs, rm)/VAR(rm)
B8: 1919.05 | D8: 8993.85 | E8: =B8/B9-1 -> 0.052053067 | F8: =D8/D9-1 -> 0.0076804141 | I8: Risk Free Rate | J8: 0.0706 | K8: RBI's 10 Yr Givt Bond yield as proxy for risk free rate
B9: 1824.1 | D9: 8925.3 | E9: =B9/B10-1 -> 0.0232519 | F9: =D9/D10-1 -> -0.0075060048 | I9: Equity Risk Premium | J9: 0.0708 | K9: Aswath Damodaran's Website
B10: 1782.65 | D10: 8992.8 | E10: =B10/B11-1 -> -0.029004848 | F10: =D10/D11-1 -> -0.029562684
B11: 1835.9 | D11: 9266.75 | E11: =B11/B12-1 -> 0.016640363 | F11: =D11/D12-1 -> 0.00052905197 | I11: Cost Of Equity | J11: =J8+(J7*J9) -> 0.13198408 | K11: Ke = Rf + B(ERP)
B12: 1805.85 | D12: 9261.85 | E12: =B12/B13-1 -> -0.01187382 | F12: =D12/D13-1 -> 0.031219903
B13: 1827.55 | D13: 8981.45 | E13: =B13/B14-1 -> -0.031838529 | F13: =D13/D14-1 -> -0.02240593 | I13: Market Value of Equity | J13: =L2*L3 -> 109559.45
B14: 1887.65 | D14: 9187.3 | E14: =B14/B15-1 -> 0.012144772 | F14: =D14/D15-1 -> -0.013592587 | I14: Value Of Debt | J14: =('Schedule Populated '!J53+'Schedule Populated '!J57) -> 742.92139
B15: 1865 | D15: 9313.9 | E15: =B15/B16-1 -> -0.015727254 | F15: =D15/D16-1 -> 0.017423316 | I15: Cost of Debt | J15: ='Schedule Populated '!J65 -> 0.11359447
B16: 1894.8 | D16: 9154.4 | E16: =B16/B17-1 -> -0.020876395 | F16: =D16/D17-1 -> -0.013778913 | I16: =I11 -> Cost Of Equity | J16: =J11 -> 0.13198408
B17: 1935.2 | D17: 9282.3 | E17: =B17/B18-1 -> -0.0040656683 | F17: =D17/D18-1 -> -0.010510719 | I17: Proportion of Debt | J17: =J14/SUM($J$13:$J$14) -> 0.0067353165
B18: 1943.1 | D18: 9380.9 | E18: =B18/B19-1 -> -0.013779977 | F18: =D18/D19-1 -> -0.01805126 | I18: Proportion of Equity | J18: =1-J17 -> 0.99326468
B19: 1970.25 | D19: 9553.35 | E19: =B19/B20-1 -> -0.090667836 | F19: =D19/D20-1 -> -0.031090579 | I19: Effective Tax rate | J19: 0.2517
B20: 2166.7 | D20: 9859.9 | E20: =B20/B21-1 -> 0.08297096 | F20: =D20/D21-1 -> 0.060945822 | I20: WACC | J20: =(J15*J17*(1-J19))+(J18*J16) -> 0.13166764
B21: 2000.7 | D21: 9293.5 | E21: =B21/B22-1 -> 0.017986618 | F21: =D21/D22-1 -> 0.0095485357 | K21: Terminal Growth Rate Calculation
B22: 1965.35 | D22: 9205.6 | E22: =B22/B23-1 -> -0.030294807 | F22: =D22/D23-1 -> -0.0070435449 | K22: GDP India | L22: 0.065 | M22: 0.4
B23: 2026.75 | D23: 9270.9 | E23: =B23/B24-1 -> 0.013223017 | F23: =D23/D24-1 -> 0.0078105891 | K23: India Two Wheeler Sector Growth | L23: 0.07 | M23: 0.3
B24: 2000.3 | D24: 9199.05 | E24: =B24/B25-1 -> 0.019209212 | F24: =D24/D25-1 -> -0.0056693509 | K24: Global Motorcycle Market Growth | L24: 0.045 | M24: 0.2
B25: 1962.6 | D25: 9251.5 | E25: =B25/B26-1 -> -0.060349987 | F25: =D25/D26-1 -> 0.0013312841 | K25: India Automobile Export Growth | L25: 0.075 | M25: 0.1
B26: 2088.65 | D26: 9239.2 | E26: =B26/B27-1 -> -0.012131675 | F26: =D26/D27-1 -> 0.0046376087 | K26: Terminal Growth Rate | M26: =L22*M22+L23*M23+L24*M24+L25*M25 -> 0.0635
B27: 2114.3 | D27: 9196.55 | E27: =B27/B28-1 -> -0.03350704 | F27: =D27/D28-1 -> -0.019928492
B28: 2187.6 | D28: 9383.55 | E28: =B28/B29-1 -> -0.023981083 | F28: =D28/D29-1 -> 0.026337809
B29: 2241.35 | D29: 9142.75 | E29: =B29/B30-1 -> 0.02179116 | F29: =D29/D30-1 -> 0.00064573677
B30: 2193.55 | D30: 9136.85 | E30: =B30/B31-1 -> 0.059404506 | F30: =D30/D31-1 -> 0.035542459
B31: 2070.55 | D31: 8823.25 | E31: =B31/B32-1 -> -0.0014227152 | F31: =D31/D32-1 -> -0.0062900519
B32: 2073.5 | D32: 8879.1 | E32: =B32/B33-1 -> 0.024659024 | F32: =D32/D33-1 -> -0.020674898
B33: 2023.6 | D33: 9066.55 | E33: =B33/B34-1 -> -0.04524652 | F33: =D33/D34-1 -> -0.0043596431
B34: 2119.5 | D34: 9106.25 | E34: =B34/B35-1 -> -0.014461081 | F34: =D34/D35-1 -> 0.0074121194
B35: 2150.6 | D35: 9039.25 | E35: =B35/B36-1 -> 0.017481608 | F35: =D35/D36-1 -> 0.001129687
B36: 2113.65 | D36: 9029.05 | E36: =B36/B37-1 -> -0.028497231 | F36: =D36/D37-1 -> -0.030692596
B37: 2175.65 | D37: 9314.95 | E37: =B37/B38-1 -> -0.053283147 | F37: =D37/D38-1 -> -0.018456075
B38: 2298.1 | D38: 9490.1 | E38: =B38/B39-1 -> -0.02657941 | F38: =D38/D39-1 -> -0.009415154
... B1234: 3772.05 | D1234: 23591.95 | E1234: =B1234/B1235-1 -> 0.013188466 | F1234: =D1234/D1235-1 -> 0.00308682
B1235: 3722.95 | D1235: 23519.35

Sheet FCFF
B2: Free Cashflow to Firm Calculation | C2: 2026 | D2: 2027 | E2: 2028 | F2: 2029 | G2: 2030 | H2: 2031 | I2: 2032 | J2: 2033 | K2: 2034 | L2: 2035 | M2: 2036 | N2: 2037 | O2: 2038 | P2: 2039 | Q2: 2040E
B3: EBIT | C3: ='P&L'!J26 -> 7070.3087 | D3: ='P&L'!K26 -> 8145.9282 | E3: ='P&L'!L26 -> 8867.2643 | F3: ='P&L'!M26 -> 9906.5725 | G3: ='P&L'!N26 -> 10607.814
B5: EBIT(1-t) (or NOPAT) | C5: =C3*(1-$C$16) -> 5290.712 | D5: =D3*(1-$C$16) -> 6095.5981 | E5: =E3*(1-$C$16) -> 6635.3739 | F5: =F3*(1-$C$16) -> 7413.0882 | G5: =G3*(1-$C$16) -> 7937.8275
B6: Add Depreciation | C6: ='P&L'!J14 -> 845.69632 | D6: ='P&L'!K14 -> 913.30015 | E6: ='P&L'!L14 -> 998.76173 | F6: ='P&L'!M14 -> 1094.7435 | G6: ='P&L'!N14 -> 1193.6248
B7: Less Change in Net Working Capital | C7: =-'Schedule Populated '!J102 -> 4188.1265 | D7: =-'Schedule Populated '!K102 -> -872.60736 | E7: =-'Schedule Populated '!L102 -> 655.56167 | F7: =-'Schedule Populated '!M102 -> -488.67789 | G7: =-'Schedule Populated '!N102 -> -834.8911
B8: Less Capital Expenditure | C8: =-'Schedule Populated '!J40 -> -1484.262 | D8: =-'Schedule Populated '!K40 -> -1522.2534 | E8: =-'Schedule Populated '!L40 -> -1643.9403 | F8: =-'Schedule Populated '!M40 -> -1797.7711 | G8: =-'Schedule Populated '!N40 -> -1970.5383
B9: FCFF | C9: =SUM(C5:C8) -> 8840.2729 | D9: =SUM(D5:D8) -> 4614.0375 | E9: =SUM(E5:E8) -> 6645.757 | F9: =SUM(F5:F8) -> 6221.3827 | G9: =SUM(G5:G8) -> 6326.0229 | H9: =G9*(1+H10) -> 7155.3591 | I9: =H9*(1+I10) -> 8045.4796 | J9: =I9*(1+J10) -> 8992.4257 | K9: =J9*(1+K10) -> 9990.5773 | L9: =K9*(1+L10) -> 11032.586 | M9: =L9*(1+M10) -> 12109.357 | N9: =M9*(1+N10) -> 13210.087 | O9: =N9*(1+O10) -> 14322.365 | ... Q9: =P9*(1+Q10) -> 16524.932
B10: FCFF Growth | D10: =D9/C9-1 -> -0.47806617 | E10: =E9/D9-1 -> 0.44033441 | F10: =F9/E9-1 -> -0.063856423 | G10: =G9/F9-1 -> 0.016819443 | H10: =AVERAGE(E10:G10) -> 0.13109914 | I10: =H10-$I$11 -> 0.12439914 | J10: =I10-$I$11 -> 0.11769914 | K10: =J10-$I$11 -> 0.11099914 | L10: =K10-$I$11 -> 0.10429914 | M10: =L10-$I$11 -> 0.097599144 | N10: =M10-$I$11 -> 0.090899144 | O10: =N10-$I$11 -> 0.084199144 | P10: =O10-$I$11 -> 0.077499144 | ... R10: =Q10-$I$11 -> 0.064099144 | S10: 0.064 | T10: 0.064 | U10: 0.064 | V10: 0.064 | W10: 0.064 | X10: 0.064 | Y10: 0.064 | Z10: 0.064
I11: 0.0067
B13: Valuation Parameters
B14: Valuation as on Specified Date | C14: 45930
B15: Date of Year Ending | C15: 46112
B16: Tax Rate (Effective Future Rate) | C16: 0.2517
B17: WACC | C17: =WACC!J20 -> 0.13166764
B18: Terminal Growth Rate | C18: =WACC!M26 -> 0.0635
B20: Years | C20: =C2 -> 2026 | D20: =D2 -> 2027 | E20: =E2 -> 2028 | F20: =F2 -> 2029 | G20: =G2 -> 2030 | H20: =H2 -> 2031 | I20: =I2 -> 2032 | J20: =J2 -> 2033 | ... Q20: =Q2 -> 2040E
B21: Time to Cashflow in Years | C21: =(C15-C14)/365 -> 0.49863014 | D21: =C21+1 -> 1.4986301 | E21: =D21+1 -> 2.4986301 | F21: =E21+1 -> 3.4986301 | G21: =F21+1 -> 4.4986301 | H21: =G21+1 -> 5.4986301 | I21: =H21+1 -> 6.4986301 | J21: =I21+1 -> 7.4986301 | K21: =J21+1 -> 8.4986301 | ... Q21: =P21+1 -> 14.49863
B22: FCFF | C22: =C9 -> 8840.2729 | D22: =D9 -> 4614.0375 | E22: =E9 -> 6645.757 | F22: =F9 -> 6221.3827 | G22: =G9 -> 6326.0229 | H22: =H9 -> 7155.3591 | I22: =I9 -> 8045.4796 | J22: =J9 -> 8992.4257 | ... Q22: =Q9 -> 16524.932
B23: Discounted FCFF | C23: =C22/(1+$C$17)^C21 -> 8311.5077 | D23: =D22/(1+$C$17)^D21 -> 3833.3313 | E23: =E22/(1+$C$17)^E21 -> 4878.8874 | F23: =F22/(1+$C$17)^F21 -> 4035.9369 | G23: =G22/(1+$C$17)^G21 -> 3626.3466 | H23: =H22/(1+$C$17)^H21 -> 3624.5249 | I23: =I22/(1+$C$17)^I21 -> 3601.2452 | J23: =J22/(1+$C$17)^J21 -> 3556.794 | ... Q23: =Q22/(1+$C$17)^Q21 -> 2749.7249
B25: Terminal Value of FCFF | C25: =Q22*(1+C18)/(C17-C18) -> 257809.5
B26: NPV of Explicit Cash Flows | C26: =SUM(C23:Q23) -> 57566.232
B27: NPV of Terminal Value | C27: =C25/(1+C17)^Q21 -> 42899.13
B28: Enterprise Value | C28: =SUM(C26:C27) -> 100465.36 | J28: =C34 -> 5456.7403 | K28: =L28-0.5% -> 0.10167682 | L28: =M28-0.5% -> 0.10667682 | M28: 0.11167682 | N28: =M28+0.5% -> 0.11667682 | O28: =N28+0.5% -> 0.12167682
B29: Less Debt | C29: =-WACC!J14 -> -742.92139 | J29: =J30-0.5% -> 0.045 | K29: 0 | L29: 0 | M29: 0 | N29: 0 | O29: 0
B30: Add Cash | C30: =CFS!E22 -> 9521.4997 | J30: =J31-0.5% -> 0.05 | K30: 0 | L30: 0 | M30: 0 | N30: 0 | O30: 0
B31: No. of Shares Outstanding | C31: =WACC!L3 -> 20.02 | J31: 0.055 | K31: 0 | L31: 0 | M31: 0 | N31: 0 | O31: 0
B32: Equity Value | C32: =C28+C29+C30 -> 109243.94 | J32: =J31+0.5% -> 0.06 | K32: 0 | L32: 0 | M32: 0 | N32: 0 | O32: 0
B33: Current Market Price | C33: =WACC!L2 -> 5472.5 | J33: =J32+0.5% -> 0.065 | K33: 0 | L33: 0 | M33: 0 | N33: 0 | O33: 0
B34: Value per Share (basis caluation) | C34: =C32/C31 -> 5456.7403
B35: Upside/Downside | C35: =C34/C33-1 -> -0.0028798044
B44: NPV of Termianl Value + NPV of Explicit Cashflow = Value of firm as of today = Enterprise value
B46: Enterprise Value = Equity Value + Debt Value - Cash

Sheet Relative Valuation
B3: P/E Based Valuation
B4: Peer Set | C4: P/E
B5: TVS Motors | C5: 52.4
B6: Bajaj Auto | C6: 26.7
B7: Eicher Motors | C7: 35.3
B9: Peer Average | C9: =AVERAGE(C5:C7) -> 38.133333
B10: Hero MotoCorp:
B11: EPS NTM | C11: =(0.5*'P&L'!J24+0.5*'P&L'!K24)/WACC!L3 -> 281.05368
B12: Target Share Price
B13: Hero MotoCorp Relative Price | C13: =C11*C9 -> 10717.514
B15: Model | C15: Price | D15: Weightages Assigned
B16: DCF suggested Price | C16: =FCFF!C34 -> 5456.7403 | D16: 0.7
B17: Relative Suggested Price | C17: =C13 -> 10717.514 | D17: 0.3
B18: Blended Target Price | C18: =SUMPRODUCT(C16:C17,D16:D17)/SUM(D16:D17) -> 7034.9723
